Workbook

Sheet README
A1: LIVING IKON BOM TRACKER AND COSTING WORKBOOK, 5 Oct 2026
A2: Same format and rate card as the PLV BOM Costing Workbook v3 (1 Oct 2026).
A4: WHAT THIS IS
B5: ITEMS lists the 36 items of the LEXI, NEW HOI AN and SIENNA catalogues, grouped by collection. Each item already has its own tab (tab name = item code; blue tabs LEXI, green NEW HOI AN, orange SIENNA).
B6: The operator reads the drawing and types component sizes, quantities and bought-in prices. Volume m³, face m², tier (grade A / A-CURVED / B / C / D) and all costs are calculated from the RATES tab. ITEMS shows status and unit cost per item for the quotation.
A8: COLOURS
B9: Blue text / white cell = you type here. Yellow cell = must be filled (item code, hardware unit price). Grey = calculated, do not type. Light blue = cost from the rate card, do not type.
A11: STEPS FOR EACH ITEM
A12: 1 | B12: Open the item tab. Code, name, collection / room, overall size and catalogue link are filled from ITEMS. If one is wrong or empty, correct it on ITEMS (or type over it).
A13: 2 | B13: Paste the DRAWING LINK on ITEMS column I (it shows on the tab). Choose FINISH RECIPE and FLATPACK Y/N. Flatpack: one PACKING row per box (inside size). Assembled: leave the boxes empty.
A14: 3 | B14: SOLID WOOD: one line per component: material, name, L, W, T in mm, qty per ONE item, EXPOSED Y/N, CURVED Y/N. The m³, m², tier and cost appear by themselves.
A15: 4 | B15: PANELS: one line per panel: panel type, L, W, T, qty, exposed faces 0 / 1 / 2. Round, oversize or laminated panel with no size: type the number of sheets in SHEETS (manual).
A16: 5 | B16: HARDWARE & BOUGHT-IN: every purchased part or outside job: description, qty, UOM and UNIT PRICE IDR. This includes drawer runners, hinges, handles, SIENNA metal frames, NEW HOI AN rattan, mirror glass, chair fabric and foam.
B17: The EXAMPLE OV-505 B tab is a filled-in item (a Standard Maldives shelf) showing what a finished tab looks like.
A18: 6 | B18: Look at the CHECK column and "Open input checks" under the summary. All must be OK / 0. Then ITEMS shows the item as "costed".
A19: 7 | B19: New item not in the catalogues: add it on a spare row of ITEMS, then right-click TEMPLATE, Duplicate, rename the copy to the item code and type the code in C1.
A21: LANGKAH SINGKAT (BAHASA INDONESIA)
A22: 1 | B22: Buka tab item (nama tab = kode item). Kode, nama, koleksi / ruangan, ukuran keseluruhan dan link katalog terisi otomatis dari ITEMS. Kalau salah atau kosong, perbaiki di ITEMS.
A23: 2 | B23: Tempel link gambar di ITEMS kolom I. Isi komponen kayu solid (ukuran mm, qty per 1 item, EXPOSED Y/N, CURVED Y/N), panel, lalu hardware / barang beli dengan HARGA SATUAN (IDR).
A24: 3 | B24: Sel abu-abu dan biru muda dihitung sistem, jangan diketik. Kolom CHECK harus OK semua. Tab RATES dan LISTS jangan diubah.
A26: RULES BUILT INTO THE FORMULAS
B27: Tier (solid wood): D = volume under 0.0005 m³ and under 300 mm · C = not exposed · A-CURVED = curved / wide board · B = section up to 40 × 40 mm and up to 1500 mm long, or shorter than 1000 mm · A = 1000 mm and longer. TIER OVERRIDE beats the rule.
B28: Tier rate = (log price + processing) × yield + carpentry labour, per m³ of finished component. Meranti = sawn price × yield + labour. Species OTHER has no rate: price it as a bought-in line.
B29: Panels: pieces per sheet from the 2440 × 1220 sheet with 5 mm kerf; whole sheets charged, unless waste on the last sheet is over 25% (then the fraction + 5% handling).
B30: Finishing: four lines (finishing materials, sanding materials, sanding labour, finishing labour) × exposed m². Exposed m² = one face (L × W × qty) per exposed solid component + exposed panel faces. Recipe NONE (RAW) = no finishing cost.
B31: Packing: carton = box size + 40 mm each way; cost = carton m² × rate + carton m³ × packing labour. Misc 5% on direct cost, overhead % on direct + misc.
A33: STILL OPEN
B34: Materials: the catalogues specify oak, Vic ash, MDF with oak veneer, rattan and metal frames. RATES only has teak, mindi, meranti and plywood with teak / mindi veneer. Decide the build material per collection, or add rates, before the costs are used for a quotation.
B35: Rate card: teak and mindi log prices are implied from the STMV ledger, not nota prices; yields for tiers A, B and D are by judgement; fasteners total, veneer prices and packing labour are estimates. Changing a blue cell on RATES re-costs every item.
B36: Finishing m² counts one face per component. For slatted items this is well below the real painted surface.
B37: The workbook gives factory cost per unit in IDR. Margin, currency and freight for the quotation are not in it.

Sheet ITEMS
A1: LIVING IKON BOM TRACKER: ITEM LIST AND COST ROLL-UP (LEXI, NEW HOI AN, SIENNA catalogues 2026)
A2: One tab per item, tab name = ITEM CODE exactly as in column C. Columns J to T, Y and Z fill by themselves from the item tab. Codes, names and sizes are as printed in the catalogues (L = length or width, W = width or depth). Blue = type or correct here.
A4: NO | B4: COLLECTION | C4: ITEM CODE (= tab name) | D4: ITEM NAME | E4: L mm | F4: W mm | G4: H mm | H4: ORDER QTY | I4: DRAWING LINK | J4: STATUS | K4: TIMBER + FASTENERS | L4: PANELS | M4: FINISHING (4 lines) | N4: HARDWARE & BOUGHT-IN | O4: PACKING | P4: MISC 4% | Q4: DIRECT COST IDR (HPP) | R4: ORDER TOTAL IDR | S4: CARTON m³ / unit | T4: OPEN CHECKS | U4: COSTED BY / NOTE | V4: CATALOGUE LINK | W4: ROOM | X4: CATALOGUE MATERIAL / FINISH | Y4: SOLID WOOD m³ / unit | Z4: FINISHING m² / unit | AA4: PANELS + HARDWARE (status check)
A6: 1 | B6: NEW HOI AN | C6: LV453-B61 | D6: DRESSER 6 DRAWERS | E6: 1500 | F6: 450 | G6: 820 | H6: 1 | I6: LV453 - B61 - DRESSER 6 DRAWERS.pdf | J6: =IF($C6="","",IF(ISERROR(INDIRECT("'"&$C6&"'!C1")),"no tab yet",IF(N(Y6)+N(AA6)=0,"tab empty",IF(N(T6)>0,"check inputs","costed")))) | K6: =IF(OR($J6="",$J6="no tab yet",$J6="tab empty"),"",IFERROR(INDIRECT("'"&$C6&"'!D87")+INDIRECT("'"&$C6&"'!D88"),"")) | L6: =IF(OR($J6="",$J6="no tab yet",$J6="tab empty"),"",IFERROR(INDIRECT("'"&$C6&"'!D89")+0,"")) | M6: =IF(OR($J6="",$J6="no tab yet",$J6="tab empty"),"",IFERROR(SUM(INDIRECT("'"&$C6&"'!D90:D93")),"")) | N6: =IF(OR($J6="",$J6="no tab yet",$J6="tab empty"),"",IFERROR(INDIRECT("'"&$C6&"'!D94")+0,"")) | O6: =IF(OR($J6="",$J6="no tab yet",$J6="tab empty"),"",IFERROR(INDIRECT("'"&$C6&"'!D95")+0,"")) | P6: =IF(OR($J6="",$J6="no tab yet",$J6="tab empty"),"",IFERROR(INDIRECT("'"&$C6&"'!D97"),"")) | Q6: =IF(OR($J6="",$J6="no tab yet",$J6="tab empty"),"",IFERROR(INDIRECT("'"&$C6&"'!D98")+0,"")) | R6: =IF(AND(ISNUMBER(H6),ISNUMBER(Q6)),H6*Q6,"") | S6: =IFERROR(INDIRECT("'"&$C6&"'!D86")+0,"") | T6: =IFERROR(INDIRECT("'"&$C6&"'!D102")+0,"") | Y6: =IFERROR(INDIRECT("'"&$C6&"'!D82")+0,"") | Z6: =IFERROR(INDIRECT("'"&$C6&"'!D84")+0,"") | AA6: =IFERROR(INDIRECT("'"&$C6&"'!D89")+INDIRECT("'"&$C6&"'!D94"),"")
J30: =IF($C30="","",IF(ISERROR(INDIRECT("'"&$C30&"'!C1")),"no tab yet",IF(N(Y30)+N(AA30)=0,"tab empty",IF(N(T30)>0,"check inputs","costed")))) | K30: =IF(OR($J30="",$J30="no tab yet",$J30="tab empty"),"",IFERROR(INDIRECT("'"&$C30&"'!D87")+INDIRECT("'"&$C30&"'!D88"),"")) | L30: =IF(OR($J30="",$J30="no tab yet",$J30="tab empty"),"",IFERROR(INDIRECT("'"&$C30&"'!D89")+0,"")) | M30: =IF(OR($J30="",$J30="no tab yet",$J30="tab empty"),"",IFERROR(SUM(INDIRECT("'"&$C30&"'!D90:D93")),"")) | N30: =IF(OR($J30="",$J30="no tab yet",$J30="tab empty"),"",IFERROR(INDIRECT("'"&$C30&"'!D94")+0,"")) | O30: =IF(OR($J30="",$J30="no tab yet",$J30="tab empty"),"",IFERROR(INDIRECT("'"&$C30&"'!D95")+0,"")) | P30: =IF(OR($J30="",$J30="no tab yet",$J30="tab empty"),"",IFERROR(INDIRECT("'"&$C30&"'!D97"),"")) | Q30: =IF(OR($J30="",$J30="no tab yet",$J30="tab empty"),"",IFERROR(INDIRECT("'"&$C30&"'!D98")+0,"")) | R30: =IF(AND(ISNUMBER(H30),ISNUMBER(Q30)),H30*Q30,"") | S30: =IFERROR(INDIRECT("'"&$C30&"'!D86")+0,"") | T30: =IFERROR(INDIRECT("'"&$C30&"'!D102")+0,"") | Y30: =IFERROR(INDIRECT("'"&$C30&"'!D82")+0,"") | Z30: =IFERROR(INDIRECT("'"&$C30&"'!D84")+0,"") | AA30: =IFERROR(INDIRECT("'"&$C30&"'!D89")+INDIRECT("'"&$C30&"'!D94"),"")
J31: =IF($C31="","",IF(ISERROR(INDIRECT("'"&$C31&"'!C1")),"no tab yet",IF(N(Y31)+N(AA31)=0,"tab empty",IF(N(T31)>0,"check inputs","costed")))) | K31: =IF(OR($J31="",$J31="no tab yet",$J31="tab empty"),"",IFERROR(INDIRECT("'"&$C31&"'!D87")+INDIRECT("'"&$C31&"'!D88"),"")) | L31: =IF(OR($J31="",$J31="no tab yet",$J31="tab empty"),"",IFERROR(INDIRECT("'"&$C31&"'!D89")+0,"")) | M31: =IF(OR($J31="",$J31="no tab yet",$J31="tab empty"),"",IFERROR(SUM(INDIRECT("'"&$C31&"'!D90:D93")),"")) | N31: =IF(OR($J31="",$J31="no tab yet",$J31="tab empty"),"",IFERROR(INDIRECT("'"&$C31&"'!D94")+0,"")) | O31: =IF(OR($J31="",$J31="no tab yet",$J31="tab empty"),"",IFERROR(INDIRECT("'"&$C31&"'!D95")+0,"")) | P31: =IF(OR($J31="",$J31="no tab yet",$J31="tab empty"),"",IFERROR(INDIRECT("'"&$C31&"'!D97"),"")) | Q31: =IF(OR($J31="",$J31="no tab yet",$J31="tab empty"),"",IFERROR(INDIRECT("'"&$C31&"'!D98")+0,"")) | R31: =IF(AND(ISNUMBER(H31),ISNUMBER(Q31)),H31*Q31,"") | S31: =IFERROR(INDIRECT("'"&$C31&"'!D86")+0,"") | T31: =IFERROR(INDIRECT("'"&$C31&"'!D102")+0,"") | Y31: =IFERROR(INDIRECT("'"&$C31&"'!D82")+0,"") | Z31: =IFERROR(INDIRECT("'"&$C31&"'!D84")+0,"") | AA31: =IFERROR(INDIRECT("'"&$C31&"'!D89")+INDIRECT("'"&$C31&"'!D94"),"")
J32: =IF($C32="","",IF(ISERROR(INDIRECT("'"&$C32&"'!C1")),"no tab yet",IF(N(Y32)+N(AA32)=0,"tab empty",IF(N(T32)>0,"check inputs","costed")))) | K32: =IF(OR($J32="",$J32="no tab yet",$J32="tab empty"),"",IFERROR(INDIRECT("'"&$C32&"'!D87")+INDIRECT("'"&$C32&"'!D88"),"")) | L32: =IF(OR($J32="",$J32="no tab yet",$J32="tab empty"),"",IFERROR(INDIRECT("'"&$C32&"'!D89")+0,"")) | M32: =IF(OR($J32="",$J32="no tab yet",$J32="tab empty"),"",IFERROR(SUM(INDIRECT("'"&$C32&"'!D90:D93")),"")) | N32: =IF(OR($J32="",$J32="no tab yet",$J32="tab empty"),"",IFERROR(INDIRECT("'"&$C32&"'!D94")+0,"")) | O32: =IF(OR($J32="",$J32="no tab yet",$J32="tab empty"),"",IFERROR(INDIRECT("'"&$C32&"'!D95")+0,"")) | P32: =IF(OR($J32="",$J32="no tab yet",$J32="tab empty"),"",IFERROR(INDIRECT("'"&$C32&"'!D97"),"")) | Q32: =IF(OR($J32="",$J32="no tab yet",$J32="tab empty"),"",IFERROR(INDIRECT("'"&$C32&"'!D98")+0,"")) | R32: =IF(AND(ISNUMBER(H32),ISNUMBER(Q32)),H32*Q32,"") | S32: =IFERROR(INDIRECT("'"&$C32&"'!D86")+0,"") | T32: =IFERROR(INDIRECT("'"&$C32&"'!D102")+0,"") | Y32: =IFERROR(INDIRECT("'"&$C32&"'!D82")+0,"") | Z32: =IFERROR(INDIRECT("'"&$C32&"'!D84")+0,"") | AA32: =IFERROR(INDIRECT("'"&$C32&"'!D89")+INDIRECT("'"&$C32&"'!D94"),"")
J33: =IF($C33="","",IF(ISERROR(INDIRECT("'"&$C33&"'!C1")),"no tab yet",IF(N(Y33)+N(AA33)=0,"tab empty",IF(N(T33)>0,"check inputs","costed")))) | K33: =IF(OR($J33="",$J33="no tab yet",$J33="tab empty"),"",IFERROR(INDIRECT("'"&$C33&"'!D87")+INDIRECT("'"&$C33&"'!D88"),"")) | L33: =IF(OR($J33="",$J33="no tab yet",$J33="tab empty"),"",IFERROR(INDIRECT("'"&$C33&"'!D89")+0,"")) | M33: =IF(OR($J33="",$J33="no tab yet",$J33="tab empty"),"",IFERROR(SUM(INDIRECT("'"&$C33&"'!D90:D93")),"")) | N33: =IF(OR($J33="",$J33="no tab yet",$J33="tab empty"),"",IFERROR(INDIRECT("'"&$C33&"'!D94")+0,"")) | O33: =IF(OR($J33="",$J33="no tab yet",$J33="tab empty"),"",IFERROR(INDIRECT("'"&$C33&"'!D95")+0,"")) | P33: =IF(OR($J33="",$J33="no tab yet",$J33="tab empty"),"",IFERROR(INDIRECT("'"&$C33&"'!D97"),"")) | Q33: =IF(OR($J33="",$J33="no tab yet",$J33="tab empty"),"",IFERROR(INDIRECT("'"&$C33&"'!D98")+0,"")) | R33: =IF(AND(ISNUMBER(H33),ISNUMBER(Q33)),H33*Q33,"") | S33: =IFERROR(INDIRECT("'"&$C33&"'!D86")+0,"") | T33: =IFERROR(INDIRECT("'"&$C33&"'!D102")+0,"") | Y33: =IFERROR(INDIRECT("'"&$C33&"'!D82")+0,"") | Z33: =IFERROR(INDIRECT("'"&$C33&"'!D84")+0,"") | AA33: =IFERROR(INDIRECT("'"&$C33&"'!D89")+INDIRECT("'"&$C33&"'!D94"),"")
J34: =IF($C34="","",IF(ISERROR(INDIRECT("'"&$C34&"'!C1")),"no tab yet",IF(N(Y34)+N(AA34)=0,"tab empty",IF(N(T34)>0,"check inputs","costed")))) | K34: =IF(OR($J34="",$J34="no tab yet",$J34="tab empty"),"",IFERROR(INDIRECT("'"&$C34&"'!D87")+INDIRECT("'"&$C34&"'!D88"),"")) | L34: =IF(OR($J34="",$J34="no tab yet",$J34="tab empty"),"",IFERROR(INDIRECT("'"&$C34&"'!D89")+0,"")) | M34: =IF(OR($J34="",$J34="no tab yet",$J34="tab empty"),"",IFERROR(SUM(INDIRECT("'"&$C34&"'!D90:D93")),"")) | N34: =IF(OR($J34="",$J34="no tab yet",$J34="tab empty"),"",IFERROR(INDIRECT("'"&$C34&"'!D94")+0,"")) | O34: =IF(OR($J34="",$J34="no tab yet",$J34="tab empty"),"",IFERROR(INDIRECT("'"&$C34&"'!D95")+0,"")) | P34: =IF(OR($J34="",$J34="no tab yet",$J34="tab empty"),"",IFERROR(INDIRECT("'"&$C34&"'!D97"),"")) | Q34: =IF(OR($J34="",$J34="no tab yet",$J34="tab empty"),"",IFERROR(INDIRECT("'"&$C34&"'!D98")+0,"")) | R34: =IF(AND(ISNUMBER(H34),ISNUMBER(Q34)),H34*Q34,"") | S34: =IFERROR(INDIRECT("'"&$C34&"'!D86")+0,"") | T34: =IFERROR(INDIRECT("'"&$C34&"'!D102")+0,"") | Y34: =IFERROR(INDIRECT("'"&$C34&"'!D82")+0,"") | Z34: =IFERROR(INDIRECT("'"&$C34&"'!D84")+0,"") | AA34: =IFERROR(INDIRECT("'"&$C34&"'!D89")+INDIRECT("'"&$C34&"'!D94"),"")
J35: =IF($C35="","",IF(ISERROR(INDIRECT("'"&$C35&"'!C1")),"no tab yet",IF(N(Y35)+N(AA35)=0,"tab empty",IF(N(T35)>0,"check inputs","costed")))) | K35: =IF(OR($J35="",$J35="no tab yet",$J35="tab empty"),"",IFERROR(INDIRECT("'"&$C35&"'!D87")+INDIRECT("'"&$C35&"'!D88"),"")) | L35: =IF(OR($J35="",$J35="no tab yet",$J35="tab empty"),"",IFERROR(INDIRECT("'"&$C35&"'!D89")+0,"")) | M35: =IF(OR($J35="",$J35="no tab yet",$J35="tab empty"),"",IFERROR(SUM(INDIRECT("'"&$C35&"'!D90:D93")),"")) | N35: =IF(OR($J35="",$J35="no tab yet",$J35="tab empty"),"",IFERROR(INDIRECT("'"&$C35&"'!D94")+0,"")) | O35: =IF(OR($J35="",$J35="no tab yet",$J35="tab empty"),"",IFERROR(INDIRECT("'"&$C35&"'!D95")+0,"")) | P35: =IF(OR($J35="",$J35="no tab yet",$J35="tab empty"),"",IFERROR(INDIRECT("'"&$C35&"'!D97"),"")) | Q35: =IF(OR($J35="",$J35="no tab yet",$J35="tab empty"),"",IFERROR(INDIRECT("'"&$C35&"'!D98")+0,"")) | R35: =IF(AND(ISNUMBER(H35),ISNUMBER(Q35)),H35*Q35,"") | S35: =IFERROR(INDIRECT("'"&$C35&"'!D86")+0,"") | T35: =IFERROR(INDIRECT("'"&$C35&"'!D102")+0,"") | Y35: =IFERROR(INDIRECT("'"&$C35&"'!D82")+0,"") | Z35: =IFERROR(INDIRECT("'"&$C35&"'!D84")+0,"") | AA35: =IFERROR(INDIRECT("'"&$C35&"'!D89")+INDIRECT("'"&$C35&"'!D94"),"")
J36: =IF($C36="","",IF(ISERROR(INDIRECT("'"&$C36&"'!C1")),"no tab yet",IF(N(Y36)+N(AA36)=0,"tab empty",IF(N(T36)>0,"check inputs","costed")))) | K36: =IF(OR($J36="",$J36="no tab yet",$J36="tab empty"),"",IFERROR(INDIRECT("'"&$C36&"'!D87")+INDIRECT("'"&$C36&"'!D88"),"")) | L36: =IF(OR($J36="",$J36="no tab yet",$J36="tab empty"),"",IFERROR(INDIRECT("'"&$C36&"'!D89")+0,"")) | M36: =IF(OR($J36="",$J36="no tab yet",$J36="tab empty"),"",IFERROR(SUM(INDIRECT("'"&$C36&"'!D90:D93")),"")) | N36: =IF(OR($J36="",$J36="no tab yet",$J36="tab empty"),"",IFERROR(INDIRECT("'"&$C36&"'!D94")+0,"")) | O36: =IF(OR($J36="",$J36="no tab yet",$J36="tab empty"),"",IFERROR(INDIRECT("'"&$C36&"'!D95")+0,"")) | P36: =IF(OR($J36="",$J36="no tab yet",$J36="tab empty"),"",IFERROR(INDIRECT("'"&$C36&"'!D97"),"")) | Q36: =IF(OR($J36="",$J36="no tab yet",$J36="tab empty"),"",IFERROR(INDIRECT("'"&$C36&"'!D98")+0,"")) | R36: =IF(AND(ISNUMBER(H36),ISNUMBER(Q36)),H36*Q36,"") | S36: =IFERROR(INDIRECT("'"&$C36&"'!D86")+0,"") | T36: =IFERROR(INDIRECT("'"&$C36&"'!D102")+0,"") | Y36: =IFERROR(INDIRECT("'"&$C36&"'!D82")+0,"") | Z36: =IFERROR(INDIRECT("'"&$C36&"'!D84")+0,"") | AA36: =IFERROR(INDIRECT("'"&$C36&"'!D89")+INDIRECT("'"&$C36&"'!D94"),"")
J37: =IF($C37="","",IF(ISERROR(INDIRECT("'"&$C37&"'!C1")),"no tab yet",IF(N(Y37)+N(AA37)=0,"tab empty",IF(N(T37)>0,"check inputs","costed")))) | K37: =IF(OR($J37="",$J37="no tab yet",$J37="tab empty"),"",IFERROR(INDIRECT("'"&$C37&"'!D87")+INDIRECT("'"&$C37&"'!D88"),"")) | L37: =IF(OR($J37="",$J37="no tab yet",$J37="tab empty"),"",IFERROR(INDIRECT("'"&$C37&"'!D89")+0,"")) | M37: =IF(OR($J37="",$J37="no tab yet",$J37="tab empty"),"",IFERROR(SUM(INDIRECT("'"&$C37&"'!D90:D93")),"")) | N37: =IF(OR($J37="",$J37="no tab yet",$J37="tab empty"),"",IFERROR(INDIRECT("'"&$C37&"'!D94")+0,"")) | O37: =IF(OR($J37="",$J37="no tab yet",$J37="tab empty"),"",IFERROR(INDIRECT("'"&$C37&"'!D95")+0,"")) | P37: =IF(OR($J37="",$J37="no tab yet",$J37="tab empty"),"",IFERROR(INDIRECT("'"&$C37&"'!D97"),"")) | Q37: =IF(OR($J37="",$J37="no tab yet",$J37="tab empty"),"",IFERROR(INDIRECT("'"&$C37&"'!D98")+0,"")) | R37: =IF(AND(ISNUMBER(H37),ISNUMBER(Q37)),H37*Q37,"") | S37: =IFERROR(INDIRECT("'"&$C37&"'!D86")+0,"") | T37: =IFERROR(INDIRECT("'"&$C37&"'!D102")+0,"") | Y37: =IFERROR(INDIRECT("'"&$C37&"'!D82")+0,"") | Z37: =IFERROR(INDIRECT("'"&$C37&"'!D84")+0,"") | AA37: =IFERROR(INDIRECT("'"&$C37&"'!D89")+INDIRECT("'"&$C37&"'!D94"),"")
J38: =IF($C38="","",IF(ISERROR(INDIRECT("'"&$C38&"'!C1")),"no tab yet",IF(N(Y38)+N(AA38)=0,"tab empty",IF(N(T38)>0,"check inputs","costed")))) | K38: =IF(OR($J38="",$J38="no tab yet",$J38="tab empty"),"",IFERROR(INDIRECT("'"&$C38&"'!D87")+INDIRECT("'"&$C38&"'!D88"),"")) | L38: =IF(OR($J38="",$J38="no tab yet",$J38="tab empty"),"",IFERROR(INDIRECT("'"&$C38&"'!D89")+0,"")) | M38: =IF(OR($J38="",$J38="no tab yet",$J38="tab empty"),"",IFERROR(SUM(INDIRECT("'"&$C38&"'!D90:D93")),"")) | N38: =IF(OR($J38="",$J38="no tab yet",$J38="tab empty"),"",IFERROR(INDIRECT("'"&$C38&"'!D94")+0,"")) | O38: =IF(OR($J38="",$J38="no tab yet",$J38="tab empty"),"",IFERROR(INDIRECT("'"&$C38&"'!D95")+0,"")) | P38: =IF(OR($J38="",$J38="no tab yet",$J38="tab empty"),"",IFERROR(INDIRECT("'"&$C38&"'!D97"),"")) | Q38: =IF(OR($J38="",$J38="no tab yet",$J38="tab empty"),"",IFERROR(INDIRECT("'"&$C38&"'!D98")+0,"")) | R38: =IF(AND(ISNUMBER(H38),ISNUMBER(Q38)),H38*Q38,"") | S38: =IFERROR(INDIRECT("'"&$C38&"'!D86")+0,"") | T38: =IFERROR(INDIRECT("'"&$C38&"'!D102")+0,"") | Y38: =IFERROR(INDIRECT("'"&$C38&"'!D82")+0,"") | Z38: =IFERROR(INDIRECT("'"&$C38&"'!D84")+0,"") | AA38: =IFERROR(INDIRECT("'"&$C38&"'!D89")+INDIRECT("'"&$C38&"'!D94"),"")
J39: =IF($C39="","",IF(ISERROR(INDIRECT("'"&$C39&"'!C1")),"no tab yet",IF(N(Y39)+N(AA39)=0,"tab empty",IF(N(T39)>0,"check inputs","costed")))) | K39: =IF(OR($J39="",$J39="no tab yet",$J39="tab empty"),"",IFERROR(INDIRECT("'"&$C39&"'!D87")+INDIRECT("'"&$C39&"'!D88"),"")) | L39: =IF(OR($J39="",$J39="no tab yet",$J39="tab empty"),"",IFERROR(INDIRECT("'"&$C39&"'!D89")+0,"")) | M39: =IF(OR($J39="",$J39="no tab yet",$J39="tab empty"),"",IFERROR(SUM(INDIRECT("'"&$C39&"'!D90:D93")),"")) | N39: =IF(OR($J39="",$J39="no tab yet",$J39="tab empty"),"",IFERROR(INDIRECT("'"&$C39&"'!D94")+0,"")) | O39: =IF(OR($J39="",$J39="no tab yet",$J39="tab empty"),"",IFERROR(INDIRECT("'"&$C39&"'!D95")+0,"")) | P39: =IF(OR($J39="",$J39="no tab yet",$J39="tab empty"),"",IFERROR(INDIRECT("'"&$C39&"'!D97"),"")) | Q39: =IF(OR($J39="",$J39="no tab yet",$J39="tab empty"),"",IFERROR(INDIRECT("'"&$C39&"'!D98")+0,"")) | R39: =IF(AND(ISNUMBER(H39),ISNUMBER(Q39)),H39*Q39,"") | S39: =IFERROR(INDIRECT("'"&$C39&"'!D86")+0,"") | T39: =IFERROR(INDIRECT("'"&$C39&"'!D102")+0,"") | Y39: =IFERROR(INDIRECT("'"&$C39&"'!D82")+0,"") | Z39: =IFERROR(INDIRECT("'"&$C39&"'!D84")+0,"") | AA39: =IFERROR(INDIRECT("'"&$C39&"'!D89")+INDIRECT("'"&$C39&"'!D94"),"")
J40: =IF($C40="","",IF(ISERROR(INDIRECT("'"&$C40&"'!C1")),"no tab yet",IF(N(Y40)+N(AA40)=0,"tab empty",IF(N(T40)>0,"check inputs","costed")))) | K40: =IF(OR($J40="",$J40="no tab yet",$J40="tab empty"),"",IFERROR(INDIRECT("'"&$C40&"'!D87")+INDIRECT("'"&$C40&"'!D88"),"")) | L40: =IF(OR($J40="",$J40="no tab yet",$J40="tab empty"),"",IFERROR(INDIRECT("'"&$C40&"'!D89")+0,"")) | M40: =IF(OR($J40="",$J40="no tab yet",$J40="tab empty"),"",IFERROR(SUM(INDIRECT("'"&$C40&"'!D90:D93")),"")) | N40: =IF(OR($J40="",$J40="no tab yet",$J40="tab empty"),"",IFERROR(INDIRECT("'"&$C40&"'!D94")+0,"")) | O40: =IF(OR($J40="",$J40="no tab yet",$J40="tab empty"),"",IFERROR(INDIRECT("'"&$C40&"'!D95")+0,"")) | P40: =IF(OR($J40="",$J40="no tab yet",$J40="tab empty"),"",IFERROR(INDIRECT("'"&$C40&"'!D97"),"")) | Q40: =IF(OR($J40="",$J40="no tab yet",$J40="tab empty"),"",IFERROR(INDIRECT("'"&$C40&"'!D98")+0,"")) | R40: =IF(AND(ISNUMBER(H40),ISNUMBER(Q40)),H40*Q40,"") | S40: =IFERROR(INDIRECT("'"&$C40&"'!D86")+0,"") | T40: =IFERROR(INDIRECT("'"&$C40&"'!D102")+0,"") | Y40: =IFERROR(INDIRECT("'"&$C40&"'!D82")+0,"") | Z40: =IFERROR(INDIRECT("'"&$C40&"'!D84")+0,"") | AA40: =IFERROR(INDIRECT("'"&$C40&"'!D89")+INDIRECT("'"&$C40&"'!D94"),"")
J41: =IF($C41="","",IF(ISERROR(INDIRECT("'"&$C41&"'!C1")),"no tab yet",IF(N(Y41)+N(AA41)=0,"tab empty",IF(N(T41)>0,"check inputs","costed")))) | K41: =IF(OR($J41="",$J41="no tab yet",$J41="tab empty"),"",IFERROR(INDIRECT("'"&$C41&"'!D87")+INDIRECT("'"&$C41&"'!D88"),"")) | L41: =IF(OR($J41="",$J41="no tab yet",$J41="tab empty"),"",IFERROR(INDIRECT("'"&$C41&"'!D89")+0,"")) | M41: =IF(OR($J41="",$J41="no tab yet",$J41="tab empty"),"",IFERROR(SUM(INDIRECT("'"&$C41&"'!D90:D93")),"")) | N41: =IF(OR($J41="",$J41="no tab yet",$J41="tab empty"),"",IFERROR(INDIRECT("'"&$C41&"'!D94")+0,"")) | O41: =IF(OR($J41="",$J41="no tab yet",$J41="tab empty"),"",IFERROR(INDIRECT("'"&$C41&"'!D95")+0,"")) | P41: =IF(OR($J41="",$J41="no tab yet",$J41="tab empty"),"",IFERROR(INDIRECT("'"&$C41&"'!D97"),"")) | Q41: =IF(OR($J41="",$J41="no tab yet",$J41="tab empty"),"",IFERROR(INDIRECT("'"&$C41&"'!D98")+0,"")) | R41: =IF(AND(ISNUMBER(H41),ISNUMBER(Q41)),H41*Q41,"") | S41: =IFERROR(INDIRECT("'"&$C41&"'!D86")+0,"") | T41: =IFERROR(INDIRECT("'"&$C41&"'!D102")+0,"") | Y41: =IFERROR(INDIRECT("'"&$C41&"'!D82")+0,"") | Z41: =IFERROR(INDIRECT("'"&$C41&"'!D84")+0,"") | AA41: =IFERROR(INDIRECT("'"&$C41&"'!D89")+INDIRECT("'"&$C41&"'!D94"),"")
... J53: =IF($C53="","",IF(ISERROR(INDIRECT("'"&$C53&"'!C1")),"no tab yet",IF(N(Y53)+N(AA53)=0,"tab empty",IF(N(T53)>0,"check inputs","costed")))) | K53: =IF(OR($J53="",$J53="no tab yet",$J53="tab empty"),"",IFERROR(INDIRECT("'"&$C53&"'!D87")+INDIRECT("'"&$C53&"'!D88"),"")) | L53: =IF(OR($J53="",$J53="no tab yet",$J53="tab empty"),"",IFERROR(INDIRECT("'"&$C53&"'!D89")+0,"")) | M53: =IF(OR($J53="",$J53="no tab yet",$J53="tab empty"),"",IFERROR(SUM(INDIRECT("'"&$C53&"'!D90:D93")),"")) | N53: =IF(OR($J53="",$J53="no tab yet",$J53="tab empty"),"",IFERROR(INDIRECT("'"&$C53&"'!D94")+0,"")) | O53: =IF(OR($J53="",$J53="no tab yet",$J53="tab empty"),"",IFERROR(INDIRECT("'"&$C53&"'!D95")+0,"")) | P53: =IF(OR($J53="",$J53="no tab yet",$J53="tab empty"),"",IFERROR(INDIRECT("'"&$C53&"'!D97"),"")) | Q53: =IF(OR($J53="",$J53="no tab yet",$J53="tab empty"),"",IFERROR(INDIRECT("'"&$C53&"'!D98")+0,"")) | R53: =IF(AND(ISNUMBER(H53),ISNUMBER(Q53)),H53*Q53,"") | S53: =IFERROR(INDIRECT("'"&$C53&"'!D86")+0,"") | T53: =IFERROR(INDIRECT("'"&$C53&"'!D102")+0,"") | Y53: =IFERROR(INDIRECT("'"&$C53&"'!D82")+0,"") | Z53: =IFERROR(INDIRECT("'"&$C53&"'!D84")+0,"") | AA53: =IFERROR(INDIRECT("'"&$C53&"'!D89")+INDIRECT("'"&$C53&"'!D94"),"")
J54: =COUNTIF(J5:J53,"costed")&" costed / "&COUNTA(C5:C53)&" items" | Q54: =SUM(Q5:Q53) | R54: =SUM(R5:R53) | S54: =SUM(S5:S53) | Y54: =SUM(Y5:Y53) | Z54: =SUM(Z5:Z53)
J57: COSTED | Q57: UNIT COST IDR, sum | R57: ORDER TOTAL IDR | S57: CARTON m³, sum | Y57: SOLID WOOD m³, sum | Z57: FINISHING m², sum
J58: =COUNTIFS($B$5:$B$53,$D58,$J$5:$J$53,"costed") | Q58: =SUMIF($B$5:$B$53,$D58,Q$5:Q$53) | R58: =SUMIF($B$5:$B$53,$D58,R$5:R$53) | S58: =SUMIF($B$5:$B$53,$D58,S$5:S$53) | Y58: =SUMIF($B$5:$B$53,$D58,Y$5:Y$53) | Z58: =SUMIF($B$5:$B$53,$D58,Z$5:Z$53)
J59: =COUNTIFS($B$5:$B$53,$D59,$J$5:$J$53,"costed") | Q59: =SUMIF($B$5:$B$53,$D59,Q$5:Q$53) | R59: =SUMIF($B$5:$B$53,$D59,R$5:R$53) | S59: =SUMIF($B$5:$B$53,$D59,S$5:S$53) | Y59: =SUMIF($B$5:$B$53,$D59,Y$5:Y$53) | Z59: =SUMIF($B$5:$B$53,$D59,Z$5:Z$53)
J60: =COUNTIFS($B$5:$B$53,$D60,$J$5:$J$53,"costed") | Q60: =SUMIF($B$5:$B$53,$D60,Q$5:Q$53) | R60: =SUMIF($B$5:$B$53,$D60,R$5:R$53) | S60: =SUMIF($B$5:$B$53,$D60,S$5:S$53) | Y60: =SUMIF($B$5:$B$53,$D60,Y$5:Y$53) | Z60: =SUMIF($B$5:$B$53,$D60,Z$5:Z$53)

Sheet TEMPLATE
A1: ITEM CODE | D1: OVERALL L mm | G1: {=IFERROR(IF(INDEX(ITEMS!$E$5:$E$120,MATCH($C$1,ITEMS!$C$5:$C$120,0))="","",INDEX(ITEMS!$E$5:$E$120,MATCH($C$1,ITEMS!$C$5:$C$120,0))),"")} | L1: =IF(G6="","photo",_xludf.IMAGE(G6))
A2: ITEM NAME | C2: {=IFERROR(IF(INDEX(ITEMS!$D$5:$D$120,MATCH($C$1,ITEMS!$C$5:$C$120,0))="","",INDEX(ITEMS!$D$5:$D$120,MATCH($C$1,ITEMS!$C$5:$C$120,0))),"")} | D2: OVERALL W mm | G2: {=IFERROR(IF(INDEX(ITEMS!$F$5:$F$120,MATCH($C$1,ITEMS!$C$5:$C$120,0))="","",INDEX(ITEMS!$F$5:$F$120,MATCH($C$1,ITEMS!$C$5:$C$120,0))),"")}
A3: COLLECTION / ROOM | C3: {=IFERROR(INDEX(ITEMS!$B$5:$B$120,MATCH($C$1,ITEMS!$C$5:$C$120,0))&" / "&INDEX(ITEMS!$W$5:$W$120,MATCH($C$1,ITEMS!$C$5:$C$120,0)),"")} | D3: OVERALL H mm | G3: {=IFERROR(IF(INDEX(ITEMS!$G$5:$G$120,MATCH($C$1,ITEMS!$C$5:$C$120,0))="","",INDEX(ITEMS!$G$5:$G$120,MATCH($C$1,ITEMS!$C$5:$C$120,0))),"")}
A4: ORDER QTY | C4: {=IFERROR(IF(INDEX(ITEMS!$H$5:$H$120,MATCH($C$1,ITEMS!$C$5:$C$120,0))="","",INDEX(ITEMS!$H$5:$H$120,MATCH($C$1,ITEMS!$C$5:$C$120,0))),"")} | D4: DRAWING LINK | G4: {=IFERROR(IF(INDEX(ITEMS!$I$5:$I$120,MATCH($C$1,ITEMS!$C$5:$C$120,0))="","",INDEX(ITEMS!$I$5:$I$120,MATCH($C$1,ITEMS!$C$5:$C$120,0))),"")}
A5: FINISH RECIPE | D5: SPEC LINK | G5: {=IFERROR(IF(INDEX(ITEMS!$V$5:$V$120,MATCH($C$1,ITEMS!$C$5:$C$120,0))="","",INDEX(ITEMS!$V$5:$V$120,MATCH($C$1,ITEMS!$C$5:$C$120,0))),"")}
A6: FLATPACK? (Y/N) | D6: PHOTO LINK
A7: NOTES | C7: {=IFERROR(IF(INDEX(ITEMS!$X$5:$X$120,MATCH($C$1,ITEMS!$C$5:$C$120,0))="","",INDEX(ITEMS!$X$5:$X$120,MATCH($C$1,ITEMS!$C$5:$C$120,0))),"")} | D7: REVISION / DATE
A9: PACKING: assembled = leave boxes blank (system uses overall size + 40 mm as 1 carton). Flatpack = one row per box.
A10: BOX | B10: CONTENTS | D10: L mm | E10: W mm | F10: H mm | G10: QTY | H10: CARTON L | I10: CARTON W | J10: CARTON H | L10: m² 6 sides (calc) | M10: m³ (calc)
A11: 1 | H11: =IF(D11="","",D11+LISTS!$F$9) | I11: =IF(E11="","",E11+LISTS!$F$9) | J11: =IF(F11="","",F11+LISTS!$F$9) | L11: =IF(H11="","",2*(H11*I11+H11*J11+I11*J11)/1000000*IF(G11="",1,G11)) | M11: =IF(H11="","",H11*I11*J11/1000000000*IF(G11="",1,G11))
A12: 2 | H12: =IF(D12="","",D12+LISTS!$F$9) | I12: =IF(E12="","",E12+LISTS!$F$9) | J12: =IF(F12="","",F12+LISTS!$F$9) | L12: =IF(H12="","",2*(H12*I12+H12*J12+I12*J12)/1000000*IF(G12="",1,G12)) | M12: =IF(H12="","",H12*I12*J12/1000000000*IF(G12="",1,G12))
A13: 3 | H13: =IF(D13="","",D13+LISTS!$F$9) | I13: =IF(E13="","",E13+LISTS!$F$9) | J13: =IF(F13="","",F13+LISTS!$F$9) | L13: =IF(H13="","",2*(H13*I13+H13*J13+I13*J13)/1000000*IF(G13="",1,G13)) | M13: =IF(H13="","",H13*I13*J13/1000000000*IF(G13="",1,G13))
A14: 4 | H14: =IF(D14="","",D14+LISTS!$F$9) | I14: =IF(E14="","",E14+LISTS!$F$9) | J14: =IF(F14="","",F14+LISTS!$F$9) | L14: =IF(H14="","",2*(H14*I14+H14*J14+I14*J14)/1000000*IF(G14="",1,G14)) | M14: =IF(H14="","",H14*I14*J14/1000000000*IF(G14="",1,G14))
A15: TOTAL | G15: =IF(D11="",1,SUM(G11:G14)+COUNTIFS(D11:D14,"<>",G11:G14,"")) | H15: cartons | L15: =IF(D11="",IF(OR(G1="",G2="",G3=""),0,2*((G1+LISTS!$F$9)*(G2+LISTS!$F$9)+(G1+LISTS!$F$9)*(G3+LISTS!$F$9)+(G2+LISTS!$F$9)*(G3+LISTS!$F$9))/1000000),SUM(L11:L14)) | M15: =IF(D11="",IF(OR(G1="",G2="",G3=""),0,(G1+LISTS!$F$9)*(G2+LISTS!$F$9)*(G3+LISTS!$F$9)/1000000000),SUM(M11:M14))
A16: SOLID WOOD: one line per component, mm, qty per ONE item
A17: NO | B17: MATERIAL | C17: LABEL | D17: COMPONENT | E17: L mm | F17: W mm | G17: T mm | H17: QTY | I17: EXPOSED Y/N | J17: CURVED Y/N | K17: TIER OVERRIDE | L17: NOTE | M17: VOL m³ (calc) | N17: FACE m² (calc) | O17: AUTO TIER (calc) | R17: CHECK (calc) | S17: RATE (system) | T17: COST IDR (system) | U17: COST USD (system)
A18: 1 | M18: =IF(OR(E18="",F18="",G18=""),"",E18*F18*G18/1000000000*IF(H18="",1,H18)) | N18: =IF(OR(E18="",F18=""),"",E18*F18/1000000*IF(H18="",1,H18)) | O18: =IF(E18="","",IF(K18<>"",K18,IF(AND(E18*F18*G18/1000000000<LISTS!$F$4,MAX(E18,F18,G18)<LISTS!$F$5),"D",IF(I18="N","C",IF(J18="Y","A-CURVED",IF(AND(MEDIAN(E18,F18,G18)<=LISTS!$F$10,MAX(E18,F18,G18)<=LISTS!$F$11),"B",IF(MAX(E18,F18,G18)>=LISTS!$F$3,"A","B"))))))) | R18: =IF(E18="","",IF(B18="","material?",IF(OR(F18="",G18=""),"size?",IF(I18="","exposed Y/N?",IF(H18="","qty?",IF(B18="OTHER","OTHER: no rate, price it under hardware","OK")))))) | S18: {=IF(OR(O18="",M18=""),"",IF(B18="MERANTI",RATES!$C$45,IFERROR(INDEX(RATES!$C:$C,MATCH(B18&"_"&SUBSTITUTE(O18,"-CURVED","C"),RATES!$A:$A,0)),"rate?")))} | T18: =IF(ISNUMBER(S18),M18*S18,"")
A19: 2 | M19: =IF(OR(E19="",F19="",G19=""),"",E19*F19*G19/1000000000*IF(H19="",1,H19)) | N19: =IF(OR(E19="",F19=""),"",E19*F19/1000000*IF(H19="",1,H19)) | O19: =IF(E19="","",IF(K19<>"",K19,IF(AND(E19*F19*G19/1000000000<LISTS!$F$4,MAX(E19,F19,G19)<LISTS!$F$5),"D",IF(I19="N","C",IF(J19="Y","A-CURVED",IF(AND(MEDIAN(E19,F19,G19)<=LISTS!$F$10,MAX(E19,F19,G19)<=LISTS!$F$11),"B",IF(MAX(E19,F19,G19)>=LISTS!$F$3,"A","B"))))))) | R19: =IF(E19="","",IF(B19="","material?",IF(OR(F19="",G19=""),"size?",IF(I19="","exposed Y/N?",IF(H19="","qty?",IF(B19="OTHER","OTHER: no rate, price it under hardware","OK")))))) | S19: {=IF(OR(O19="",M19=""),"",IF(B19="MERANTI",RATES!$C$45,IFERROR(INDEX(RATES!$C:$C,MATCH(B19&"_"&SUBSTITUTE(O19,"-CURVED","C"),RATES!$A:$A,0)),"rate?")))} | T19: =IF(ISNUMBER(S19),M19*S19,"")
A20: 3 | M20: =IF(OR(E20="",F20="",G20=""),"",E20*F20*G20/1000000000*IF(H20="",1,H20)) | N20: =IF(OR(E20="",F20=""),"",E20*F20/1000000*IF(H20="",1,H20)) | O20: =IF(E20="","",IF(K20<>"",K20,IF(AND(E20*F20*G20/1000000000<LISTS!$F$4,MAX(E20,F20,G20)<LISTS!$F$5),"D",IF(I20="N","C",IF(J20="Y","A-CURVED",IF(AND(MEDIAN(E20,F20,G20)<=LISTS!$F$10,MAX(E20,F20,G20)<=LISTS!$F$11),"B",IF(MAX(E20,F20,G20)>=LISTS!$F$3,"A","B"))))))) | R20: =IF(E20="","",IF(B20="","material?",IF(OR(F20="",G20=""),"size?",IF(I20="","exposed Y/N?",IF(H20="","qty?",IF(B20="OTHER","OTHER: no rate, price it under hardware","OK")))))) | S20: {=IF(OR(O20="",M20=""),"",IF(B20="MERANTI",RATES!$C$45,IFERROR(INDEX(RATES!$C:$C,MATCH(B20&"_"&SUBSTITUTE(O20,"-CURVED","C"),RATES!$A:$A,0)),"rate?")))} | T20: =IF(ISNUMBER(S20),M20*S20,"")
A21: 4 | M21: =IF(OR(E21="",F21="",G21=""),"",E21*F21*G21/1000000000*IF(H21="",1,H21)) | N21: =IF(OR(E21="",F21=""),"",E21*F21/1000000*IF(H21="",1,H21)) | O21: =IF(E21="","",IF(K21<>"",K21,IF(AND(E21*F21*G21/1000000000<LISTS!$F$4,MAX(E21,F21,G21)<LISTS!$F$5),"D",IF(I21="N","C",IF(J21="Y","A-CURVED",IF(AND(MEDIAN(E21,F21,G21)<=LISTS!$F$10,MAX(E21,F21,G21)<=LISTS!$F$11),"B",IF(MAX(E21,F21,G21)>=LISTS!$F$3,"A","B"))))))) | R21: =IF(E21="","",IF(B21="","material?",IF(OR(F21="",G21=""),"size?",IF(I21="","exposed Y/N?",IF(H21="","qty?",IF(B21="OTHER","OTHER: no rate, price it under hardware","OK")))))) | S21: {=IF(OR(O21="",M21=""),"",IF(B21="MERANTI",RATES!$C$45,IFERROR(INDEX(RATES!$C:$C,MATCH(B21&"_"&SUBSTITUTE(O21,"-CURVED","C"),RATES!$A:$A,0)),"rate?")))} | T21: =IF(ISNUMBER(S21),M21*S21,"")
A22: 5 | M22: =IF(OR(E22="",F22="",G22=""),"",E22*F22*G22/1000000000*IF(H22="",1,H22)) | N22: =IF(OR(E22="",F22=""),"",E22*F22/1000000*IF(H22="",1,H22)) | O22: =IF(E22="","",IF(K22<>"",K22,IF(AND(E22*F22*G22/1000000000<LISTS!$F$4,MAX(E22,F22,G22)<LISTS!$F$5),"D",IF(I22="N","C",IF(J22="Y","A-CURVED",IF(AND(MEDIAN(E22,F22,G22)<=LISTS!$F$10,MAX(E22,F22,G22)<=LISTS!$F$11),"B",IF(MAX(E22,F22,G22)>=LISTS!$F$3,"A","B"))))))) | R22: =IF(E22="","",IF(B22="","material?",IF(OR(F22="",G22=""),"size?",IF(I22="","exposed Y/N?",IF(H22="","qty?",IF(B22="OTHER","OTHER: no rate, price it under hardware","OK")))))) | S22: {=IF(OR(O22="",M22=""),"",IF(B22="MERANTI",RATES!$C$45,IFERROR(INDEX(RATES!$C:$C,MATCH(B22&"_"&SUBSTITUTE(O22,"-CURVED","C"),RATES!$A:$A,0)),"rate?")))} | T22: =IF(ISNUMBER(S22),M22*S22,"")
A23: 6 | M23: =IF(OR(E23="",F23="",G23=""),"",E23*F23*G23/1000000000*IF(H23="",1,H23)) | N23: =IF(OR(E23="",F23=""),"",E23*F23/1000000*IF(H23="",1,H23)) | O23: =IF(E23="","",IF(K23<>"",K23,IF(AND(E23*F23*G23/1000000000<LISTS!$F$4,MAX(E23,F23,G23)<LISTS!$F$5),"D",IF(I23="N","C",IF(J23="Y","A-CURVED",IF(AND(MEDIAN(E23,F23,G23)<=LISTS!$F$10,MAX(E23,F23,G23)<=LISTS!$F$11),"B",IF(MAX(E23,F23,G23)>=LISTS!$F$3,"A","B"))))))) | R23: =IF(E23="","",IF(B23="","material?",IF(OR(F23="",G23=""),"size?",IF(I23="","exposed Y/N?",IF(H23="","qty?",IF(B23="OTHER","OTHER: no rate, price it under hardware","OK")))))) | S23: {=IF(OR(O23="",M23=""),"",IF(B23="MERANTI",RATES!$C$45,IFERROR(INDEX(RATES!$C:$C,MATCH(B23&"_"&SUBSTITUTE(O23,"-CURVED","C"),RATES!$A:$A,0)),"rate?")))} | T23: =IF(ISNUMBER(S23),M23*S23,"")
A24: 7 | M24: =IF(OR(E24="",F24="",G24=""),"",E24*F24*G24/1000000000*IF(H24="",1,H24)) | N24: =IF(OR(E24="",F24=""),"",E24*F24/1000000*IF(H24="",1,H24)) | O24: =IF(E24="","",IF(K24<>"",K24,IF(AND(E24*F24*G24/1000000000<LISTS!$F$4,MAX(E24,F24,G24)<LISTS!$F$5),"D",IF(I24="N","C",IF(J24="Y","A-CURVED",IF(AND(MEDIAN(E24,F24,G24)<=LISTS!$F$10,MAX(E24,F24,G24)<=LISTS!$F$11),"B",IF(MAX(E24,F24,G24)>=LISTS!$F$3,"A","B"))))))) | R24: =IF(E24="","",IF(B24="","material?",IF(OR(F24="",G24=""),"size?",IF(I24="","exposed Y/N?",IF(H24="","qty?",IF(B24="OTHER","OTHER: no rate, price it under hardware","OK")))))) | S24: {=IF(OR(O24="",M24=""),"",IF(B24="MERANTI",RATES!$C$45,IFERROR(INDEX(RATES!$C:$C,MATCH(B24&"_"&SUBSTITUTE(O24,"-CURVED","C"),RATES!$A:$A,0)),"rate?")))} | T24: =IF(ISNUMBER(S24),M24*S24,"")
A25: 8 | M25: =IF(OR(E25="",F25="",G25=""),"",E25*F25*G25/1000000000*IF(H25="",1,H25)) | N25: =IF(OR(E25="",F25=""),"",E25*F25/1000000*IF(H25="",1,H25)) | O25: =IF(E25="","",IF(K25<>"",K25,IF(AND(E25*F25*G25/1000000000<LISTS!$F$4,MAX(E25,F25,G25)<LISTS!$F$5),"D",IF(I25="N","C",IF(J25="Y","A-CURVED",IF(AND(MEDIAN(E25,F25,G25)<=LISTS!$F$10,MAX(E25,F25,G25)<=LISTS!$F$11),"B",IF(MAX(E25,F25,G25)>=LISTS!$F$3,"A","B"))))))) | R25: =IF(E25="","",IF(B25="","material?",IF(OR(F25="",G25=""),"size?",IF(I25="","exposed Y/N?",IF(H25="","qty?",IF(B25="OTHER","OTHER: no rate, price it under hardware","OK")))))) | S25: {=IF(OR(O25="",M25=""),"",IF(B25="MERANTI",RATES!$C$45,IFERROR(INDEX(RATES!$C:$C,MATCH(B25&"_"&SUBSTITUTE(O25,"-CURVED","C"),RATES!$A:$A,0)),"rate?")))} | T25: =IF(ISNUMBER(S25),M25*S25,"")
A26: 9 | M26: =IF(OR(E26="",F26="",G26=""),"",E26*F26*G26/1000000000*IF(H26="",1,H26)) | N26: =IF(OR(E26="",F26=""),"",E26*F26/1000000*IF(H26="",1,H26)) | O26: =IF(E26="","",IF(K26<>"",K26,IF(AND(E26*F26*G26/1000000000<LISTS!$F$4,MAX(E26,F26,G26)<LISTS!$F$5),"D",IF(I26="N","C",IF(J26="Y","A-CURVED",IF(AND(MEDIAN(E26,F26,G26)<=LISTS!$F$10,MAX(E26,F26,G26)<=LISTS!$F$11),"B",IF(MAX(E26,F26,G26)>=LISTS!$F$3,"A","B"))))))) | R26: =IF(E26="","",IF(B26="","material?",IF(OR(F26="",G26=""),"size?",IF(I26="","exposed Y/N?",IF(H26="","qty?",IF(B26="OTHER","OTHER: no rate, price it under hardware","OK")))))) | S26: {=IF(OR(O26="",M26=""),"",IF(B26="MERANTI",RATES!$C$45,IFERROR(INDEX(RATES!$C:$C,MATCH(B26&"_"&SUBSTITUTE(O26,"-CURVED","C"),RATES!$A:$A,0)),"rate?")))} | T26: =IF(ISNUMBER(S26),M26*S26,"")
A27: 10 | M27: =IF(OR(E27="",F27="",G27=""),"",E27*F27*G27/1000000000*IF(H27="",1,H27)) | N27: =IF(OR(E27="",F27=""),"",E27*F27/1000000*IF(H27="",1,H27)) | O27: =IF(E27="","",IF(K27<>"",K27,IF(AND(E27*F27*G27/1000000000<LISTS!$F$4,MAX(E27,F27,G27)<LISTS!$F$5),"D",IF(I27="N","C",IF(J27="Y","A-CURVED",IF(AND(MEDIAN(E27,F27,G27)<=LISTS!$F$10,MAX(E27,F27,G27)<=LISTS!$F$11),"B",IF(MAX(E27,F27,G27)>=LISTS!$F$3,"A","B"))))))) | R27: =IF(E27="","",IF(B27="","material?",IF(OR(F27="",G27=""),"size?",IF(I27="","exposed Y/N?",IF(H27="","qty?",IF(B27="OTHER","OTHER: no rate, price it under hardware","OK")))))) | S27: {=IF(OR(O27="",M27=""),"",IF(B27="MERANTI",RATES!$C$45,IFERROR(INDEX(RATES!$C:$C,MATCH(B27&"_"&SUBSTITUTE(O27,"-CURVED","C"),RATES!$A:$A,0)),"rate?")))} | T27: =IF(ISNUMBER(S27),M27*S27,"")
A28: 11 | M28: =IF(OR(E28="",F28="",G28=""),"",E28*F28*G28/1000000000*IF(H28="",1,H28)) | N28: =IF(OR(E28="",F28=""),"",E28*F28/1000000*IF(H28="",1,H28)) | O28: =IF(E28="","",IF(K28<>"",K28,IF(AND(E28*F28*G28/1000000000<LISTS!$F$4,MAX(E28,F28,G28)<LISTS!$F$5),"D",IF(I28="N","C",IF(J28="Y","A-CURVED",IF(AND(MEDIAN(E28,F28,G28)<=LISTS!$F$10,MAX(E28,F28,G28)<=LISTS!$F$11),"B",IF(MAX(E28,F28,G28)>=LISTS!$F$3,"A","B"))))))) | R28: =IF(E28="","",IF(B28="","material?",IF(OR(F28="",G28=""),"size?",IF(I28="","exposed Y/N?",IF(H28="","qty?",IF(B28="OTHER","OTHER: no rate, price it under hardware","OK")))))) | S28: {=IF(OR(O28="",M28=""),"",IF(B28="MERANTI",RATES!$C$45,IFERROR(INDEX(RATES!$C:$C,MATCH(B28&"_"&SUBSTITUTE(O28,"-CURVED","C"),RATES!$A:$A,0)),"rate?")))} | T28: =IF(ISNUMBER(S28),M28*S28,"")
A29: 12 | M29: =IF(OR(E29="",F29="",G29=""),"",E29*F29*G29/1000000000*IF(H29="",1,H29)) | N29: =IF(OR(E29="",F29=""),"",E29*F29/1000000*IF(H29="",1,H29)) | O29: =IF(E29="","",IF(K29<>"",K29,IF(AND(E29*F29*G29/1000000000<LISTS!$F$4,MAX(E29,F29,G29)<LISTS!$F$5),"D",IF(I29="N","C",IF(J29="Y","A-CURVED",IF(AND(MEDIAN(E29,F29,G29)<=LISTS!$F$10,MAX(E29,F29,G29)<=LISTS!$F$11),"B",IF(MAX(E29,F29,G29)>=LISTS!$F$3,"A","B"))))))) | R29: =IF(E29="","",IF(B29="","material?",IF(OR(F29="",G29=""),"size?",IF(I29="","exposed Y/N?",IF(H29="","qty?",IF(B29="OTHER","OTHER: no rate, price it under hardware","OK")))))) | S29: {=IF(OR(O29="",M29=""),"",IF(B29="MERANTI",RATES!$C$45,IFERROR(INDEX(RATES!$C:$C,MATCH(B29&"_"&SUBSTITUTE(O29,"-CURVED","C"),RATES!$A:$A,0)),"rate?")))} | T29: =IF(ISNUMBER(S29),M29*S29,"")
... A32: 15 | M32: =IF(OR(E32="",F32="",G32=""),"",E32*F32*G32/1000000000*IF(H32="",1,H32)) | N32: =IF(OR(E32="",F32=""),"",E32*F32/1000000*IF(H32="",1,H32)) | O32: =IF(E32="","",IF(K32<>"",K32,IF(AND(E32*F32*G32/1000000000<LISTS!$F$4,MAX(E32,F32,G32)<LISTS!$F$5),"D",IF(I32="N","C",IF(J32="Y","A-CURVED",IF(AND(MEDIAN(E32,F32,G32)<=LISTS!$F$10,MAX(E32,F32,G32)<=LISTS!$F$11),"B",IF(MAX(E32,F32,G32)>=LISTS!$F$3,"A","B"))))))) | R32: =IF(E32="","",IF(B32="","material?",IF(OR(F32="",G32=""),"size?",IF(I32="","exposed Y/N?",IF(H32="","qty?",IF(B32="OTHER","OTHER: no rate, price it under hardware","OK")))))) | S32: {=IF(OR(O32="",M32=""),"",IF(B32="MERANTI",RATES!$C$45,IFERROR(INDEX(RATES!$C:$C,MATCH(B32&"_"&SUBSTITUTE(O32,"-CURVED","C"),RATES!$A:$A,0)),"rate?")))} | T32: =IF(ISNUMBER(S32),M32*S32,"")
A33: METAL (hollow steel): one line per part, priced PER METRE from the RATES hollow list. MATERIAL = hollow code HOLLOW-<a>x<b>x<wall>, or METAL (= section W x T with RATES!HOLLOW_WALL)
A34: NO | B34: MATERIAL / HOLLOW CODE | C34: LABEL | D34: COMPONENT | E34: L mm | F34: W mm | G34: T mm | H34: QTY | I34: EXPOSED Y/N | L34: NOTE | M34: LENGTH m (calc) | N34: FACE m² (calc) | O34: CODE USED (calc) | R34: CHECK (calc) | S34: RATE IDR/m (system) | T34: COST IDR (system) | U34: COST USD (system)
A35: 1 | M35: =IF(E35="","",E35/1000*IF(H35="",1,H35)) | N35: =IF(OR(E35="",F35=""),"",E35*F35/1000000*IF(H35="",1,H35)) | O35: =IF(E35="","",IF(UPPER(B35)="METAL",IFERROR(IFERROR(INDEX(RATES!$A:$A,MATCH("HOLLOW-"&MIN(F35,G35)&"x"&MAX(F35,G35)&"x"&SUBSTITUTE(RATES!$C$252&"",",","."),RATES!$A:$A,0)),IFERROR(INDEX(RATES!$A:$A,MATCH("HOLLOW-"&MIN(F35,G35)&"x"&MAX(F35,G35)&"x"&"1",RATES!$A:$A,0)),IFERROR(INDEX(RATES!$A:$A,MATCH("HOLLOW-"&MIN(F35,G35)&"x"&MAX(F35,G35)&"x"&"1.2",RATES!$A:$A,0)),INDEX(RATES!$A:$A,MATCH("HOLLOW-"&MIN(F35,G35)&"x"&MAX(F35,G35)&"x"&"1.5",RATES!$A:$A,0))))),"not in list"),IFERROR(INDEX(RATES!$A:$A,MATCH(IF(LEFT(UPPER(B35),7)="HOLLOW-",UPPER(B35),"HOLLOW-"&B35),RATES!$A:$A,0)),"not in list"))) | R35: =IF(E35="","",IF(B35="","material?",IF(OR(F35="",G35=""),"size?",IF(I35="","exposed Y/N?",IF(H35="","qty?",IF(O35="not in list","hollow code?","OK")))))) | S35: =IF(E35="","",IFERROR(INDEX(RATES!$C:$C,MATCH(O35,RATES!$A:$A,0)),"rate?")) | T35: =IF(AND(ISNUMBER(S35),ISNUMBER(M35)),M35*S35,"") | U35: =IF(T35="","",T35/RATES!$C$172)
A36: 2 | M36: =IF(E36="","",E36/1000*IF(H36="",1,H36)) | N36: =IF(OR(E36="",F36=""),"",E36*F36/1000000*IF(H36="",1,H36)) | O36: =IF(E36="","",IF(UPPER(B36)="METAL",IFERROR(IFERROR(INDEX(RATES!$A:$A,MATCH("HOLLOW-"&MIN(F36,G36)&"x"&MAX(F36,G36)&"x"&SUBSTITUTE(RATES!$C$252&"",",","."),RATES!$A:$A,0)),IFERROR(INDEX(RATES!$A:$A,MATCH("HOLLOW-"&MIN(F36,G36)&"x"&MAX(F36,G36)&"x"&"1",RATES!$A:$A,0)),IFERROR(INDEX(RATES!$A:$A,MATCH("HOLLOW-"&MIN(F36,G36)&"x"&MAX(F36,G36)&"x"&"1.2",RATES!$A:$A,0)),INDEX(RATES!$A:$A,MATCH("HOLLOW-"&MIN(F36,G36)&"x"&MAX(F36,G36)&"x"&"1.5",RATES!$A:$A,0))))),"not in list"),IFERROR(INDEX(RATES!$A:$A,MATCH(IF(LEFT(UPPER(B36),7)="HOLLOW-",UPPER(B36),"HOLLOW-"&B36),RATES!$A:$A,0)),"not in list"))) | R36: =IF(E36="","",IF(B36="","material?",IF(OR(F36="",G36=""),"size?",IF(I36="","exposed Y/N?",IF(H36="","qty?",IF(O36="not in list","hollow code?","OK")))))) | S36: =IF(E36="","",IFERROR(INDEX(RATES!$C:$C,MATCH(O36,RATES!$A:$A,0)),"rate?")) | T36: =IF(AND(ISNUMBER(S36),ISNUMBER(M36)),M36*S36,"") | U36: =IF(T36="","",T36/RATES!$C$172)
A37: 3 | M37: =IF(E37="","",E37/1000*IF(H37="",1,H37)) | N37: =IF(OR(E37="",F37=""),"",E37*F37/1000000*IF(H37="",1,H37)) | O37: =IF(E37="","",IF(UPPER(B37)="METAL",IFERROR(IFERROR(INDEX(RATES!$A:$A,MATCH("HOLLOW-"&MIN(F37,G37)&"x"&MAX(F37,G37)&"x"&SUBSTITUTE(RATES!$C$252&"",",","."),RATES!$A:$A,0)),IFERROR(INDEX(RATES!$A:$A,MATCH("HOLLOW-"&MIN(F37,G37)&"x"&MAX(F37,G37)&"x"&"1",RATES!$A:$A,0)),IFERROR(INDEX(RATES!$A:$A,MATCH("HOLLOW-"&MIN(F37,G37)&"x"&MAX(F37,G37)&"x"&"1.2",RATES!$A:$A,0)),INDEX(RATES!$A:$A,MATCH("HOLLOW-"&MIN(F37,G37)&"x"&MAX(F37,G37)&"x"&"1.5",RATES!$A:$A,0))))),"not in list"),IFERROR(INDEX(RATES!$A:$A,MATCH(IF(LEFT(UPPER(B37),7)="HOLLOW-",UPPER(B37),"HOLLOW-"&B37),RATES!$A:$A,0)),"not in list"))) | R37: =IF(E37="","",IF(B37="","material?",IF(OR(F37="",G37=""),"size?",IF(I37="","exposed Y/N?",IF(H37="","qty?",IF(O37="not in list","hollow code?","OK")))))) | S37: =IF(E37="","",IFERROR(INDEX(RATES!$C:$C,MATCH(O37,RATES!$A:$A,0)),"rate?")) | T37: =IF(AND(ISNUMBER(S37),ISNUMBER(M37)),M37*S37,"") | U37: =IF(T37="","",T37/RATES!$C$172)
A38: 4 | M38: =IF(E38="","",E38/1000*IF(H38="",1,H38)) | N38: =IF(OR(E38="",F38=""),"",E38*F38/1000000*IF(H38="",1,H38)) | O38: =IF(E38="","",IF(UPPER(B38)="METAL",IFERROR(IFERROR(INDEX(RATES!$A:$A,MATCH("HOLLOW-"&MIN(F38,G38)&"x"&MAX(F38,G38)&"x"&SUBSTITUTE(RATES!$C$252&"",",","."),RATES!$A:$A,0)),IFERROR(INDEX(RATES!$A:$A,MATCH("HOLLOW-"&MIN(F38,G38)&"x"&MAX(F38,G38)&"x"&"1",RATES!$A:$A,0)),IFERROR(INDEX(RATES!$A:$A,MATCH("HOLLOW-"&MIN(F38,G38)&"x"&MAX(F38,G38)&"x"&"1.2",RATES!$A:$A,0)),INDEX(RATES!$A:$A,MATCH("HOLLOW-"&MIN(F38,G38)&"x"&MAX(F38,G38)&"x"&"1.5",RATES!$A:$A,0))))),"not in list"),IFERROR(INDEX(RATES!$A:$A,MATCH(IF(LEFT(UPPER(B38),7)="HOLLOW-",UPPER(B38),"HOLLOW-"&B38),RATES!$A:$A,0)),"not in list"))) | R38: =IF(E38="","",IF(B38="","material?",IF(OR(F38="",G38=""),"size?",IF(I38="","exposed Y/N?",IF(H38="","qty?",IF(O38="not in list","hollow code?","OK")))))) | S38: =IF(E38="","",IFERROR(INDEX(RATES!$C:$C,MATCH(O38,RATES!$A:$A,0)),"rate?")) | T38: =IF(AND(ISNUMBER(S38),ISNUMBER(M38)),M38*S38,"") | U38: =IF(T38="","",T38/RATES!$C$172)
A39: 5 | M39: =IF(E39="","",E39/1000*IF(H39="",1,H39)) | N39: =IF(OR(E39="",F39=""),"",E39*F39/1000000*IF(H39="",1,H39)) | O39: =IF(E39="","",IF(UPPER(B39)="METAL",IFERROR(IFERROR(INDEX(RATES!$A:$A,MATCH("HOLLOW-"&MIN(F39,G39)&"x"&MAX(F39,G39)&"x"&SUBSTITUTE(RATES!$C$252&"",",","."),RATES!$A:$A,0)),IFERROR(INDEX(RATES!$A:$A,MATCH("HOLLOW-"&MIN(F39,G39)&"x"&MAX(F39,G39)&"x"&"1",RATES!$A:$A,0)),IFERROR(INDEX(RATES!$A:$A,MATCH("HOLLOW-"&MIN(F39,G39)&"x"&MAX(F39,G39)&"x"&"1.2",RATES!$A:$A,0)),INDEX(RATES!$A:$A,MATCH("HOLLOW-"&MIN(F39,G39)&"x"&MAX(F39,G39)&"x"&"1.5",RATES!$A:$A,0))))),"not in list"),IFERROR(INDEX(RATES!$A:$A,MATCH(IF(LEFT(UPPER(B39),7)="HOLLOW-",UPPER(B39),"HOLLOW-"&B39),RATES!$A:$A,0)),"not in list"))) | R39: =IF(E39="","",IF(B39="","material?",IF(OR(F39="",G39=""),"size?",IF(I39="","exposed Y/N?",IF(H39="","qty?",IF(O39="not in list","hollow code?","OK")))))) | S39: =IF(E39="","",IFERROR(INDEX(RATES!$C:$C,MATCH(O39,RATES!$A:$A,0)),"rate?")) | T39: =IF(AND(ISNUMBER(S39),ISNUMBER(M39)),M39*S39,"") | U39: =IF(T39="","",T39/RATES!$C$172)
A40: 6 | M40: =IF(E40="","",E40/1000*IF(H40="",1,H40)) | N40: =IF(OR(E40="",F40=""),"",E40*F40/1000000*IF(H40="",1,H40)) | O40: =IF(E40="","",IF(UPPER(B40)="METAL",IFERROR(IFERROR(INDEX(RATES!$A:$A,MATCH("HOLLOW-"&MIN(F40,G40)&"x"&MAX(F40,G40)&"x"&SUBSTITUTE(RATES!$C$252&"",",","."),RATES!$A:$A,0)),IFERROR(INDEX(RATES!$A:$A,MATCH("HOLLOW-"&MIN(F40,G40)&"x"&MAX(F40,G40)&"x"&"1",RATES!$A:$A,0)),IFERROR(INDEX(RATES!$A:$A,MATCH("HOLLOW-"&MIN(F40,G40)&"x"&MAX(F40,G40)&"x"&"1.2",RATES!$A:$A,0)),INDEX(RATES!$A:$A,MATCH("HOLLOW-"&MIN(F40,G40)&"x"&MAX(F40,G40)&"x"&"1.5",RATES!$A:$A,0))))),"not in list"),IFERROR(INDEX(RATES!$A:$A,MATCH(IF(LEFT(UPPER(B40),7)="HOLLOW-",UPPER(B40),"HOLLOW-"&B40),RATES!$A:$A,0)),"not in list"))) | R40: =IF(E40="","",IF(B40="","material?",IF(OR(F40="",G40=""),"size?",IF(I40="","exposed Y/N?",IF(H40="","qty?",IF(O40="not in list","hollow code?","OK")))))) | S40: =IF(E40="","",IFERROR(INDEX(RATES!$C:$C,MATCH(O40,RATES!$A:$A,0)),"rate?")) | T40: =IF(AND(ISNUMBER(S40),ISNUMBER(M40)),M40*S40,"") | U40: =IF(T40="","",T40/RATES!$C$172)
A41: 7 | M41: =IF(E41="","",E41/1000*IF(H41="",1,H41)) | N41: =IF(OR(E41="",F41=""),"",E41*F41/1000000*IF(H41="",1,H41)) | O41: =IF(E41="","",IF(UPPER(B41)="METAL",IFERROR(IFERROR(INDEX(RATES!$A:$A,MATCH("HOLLOW-"&MIN(F41,G41)&"x"&MAX(F41,G41)&"x"&SUBSTITUTE(RATES!$C$252&"",",","."),RATES!$A:$A,0)),IFERROR(INDEX(RATES!$A:$A,MATCH("HOLLOW-"&MIN(F41,G41)&"x"&MAX(F41,G41)&"x"&"1",RATES!$A:$A,0)),IFERROR(INDEX(RATES!$A:$A,MATCH("HOLLOW-"&MIN(F41,G41)&"x"&MAX(F41,G41)&"x"&"1.2",RATES!$A:$A,0)),INDEX(RATES!$A:$A,MATCH("HOLLOW-"&MIN(F41,G41)&"x"&MAX(F41,G41)&"x"&"1.5",RATES!$A:$A,0))))),"not in list"),IFERROR(INDEX(RATES!$A:$A,MATCH(IF(LEFT(UPPER(B41),7)="HOLLOW-",UPPER(B41),"HOLLOW-"&B41),RATES!$A:$A,0)),"not in list"))) | R41: =IF(E41="","",IF(B41="","material?",IF(OR(F41="",G41=""),"size?",IF(I41="","exposed Y/N?",IF(H41="","qty?",IF(O41="not in list","hollow code?","OK")))))) | S41: =IF(E41="","",IFERROR(INDEX(RATES!$C:$C,MATCH(O41,RATES!$A:$A,0)),"rate?")) | T41: =IF(AND(ISNUMBER(S41),ISNUMBER(M41)),M41*S41,"") | U41: =IF(T41="","",T41/RATES!$C$172)
A42: 8 | M42: =IF(E42="","",E42/1000*IF(H42="",1,H42)) | N42: =IF(OR(E42="",F42=""),"",E42*F42/1000000*IF(H42="",1,H42)) | O42: =IF(E42="","",IF(UPPER(B42)="METAL",IFERROR(IFERROR(INDEX(RATES!$A:$A,MATCH("HOLLOW-"&MIN(F42,G42)&"x"&MAX(F42,G42)&"x"&SUBSTITUTE(RATES!$C$252&"",",","."),RATES!$A:$A,0)),IFERROR(INDEX(RATES!$A:$A,MATCH("HOLLOW-"&MIN(F42,G42)&"x"&MAX(F42,G42)&"x"&"1",RATES!$A:$A,0)),IFERROR(INDEX(RATES!$A:$A,MATCH("HOLLOW-"&MIN(F42,G42)&"x"&MAX(F42,G42)&"x"&"1.2",RATES!$A:$A,0)),INDEX(RATES!$A:$A,MATCH("HOLLOW-"&MIN(F42,G42)&"x"&MAX(F42,G42)&"x"&"1.5",RATES!$A:$A,0))))),"not in list"),IFERROR(INDEX(RATES!$A:$A,MATCH(IF(LEFT(UPPER(B42),7)="HOLLOW-",UPPER(B42),"HOLLOW-"&B42),RATES!$A:$A,0)),"not in list"))) | R42: =IF(E42="","",IF(B42="","material?",IF(OR(F42="",G42=""),"size?",IF(I42="","exposed Y/N?",IF(H42="","qty?",IF(O42="not in list","hollow code?","OK")))))) | S42: =IF(E42="","",IFERROR(INDEX(RATES!$C:$C,MATCH(O42,RATES!$A:$A,0)),"rate?")) | T42: =IF(AND(ISNUMBER(S42),ISNUMBER(M42)),M42*S42,"") | U42: =IF(T42="","",T42/RATES!$C$172)
A44: PANELS: one line per panel, L × W in mm, T = board thickness, qty per item. No size (round, oversize, laminated): enter SHEETS (manual)
A45: NO | B45: PANEL TYPE | C45: LABEL | D45: COMPONENT | E45: L mm | F45: W mm | G45: T mm | H45: QTY | I45: EXPOSED FACES (0/1/2) | K45: SHEETS (manual) | L45: NOTE | M45: VOL m³ (calc) | N45: FACE m² (calc) | O45: PIECES/SHEET (calc) | P45: SHEETS (calc) | Q45: WASTE % (calc) | R45: CHECK (calc) | S45: RATE (system) | T45: COST IDR (system) | U45: COST USD (system)
A46: 1 | M46: =IF(OR(E46="",F46="",G46=""),"",E46*F46*G46/1000000000*IF(H46="",1,H46)) | N46: =IF(OR(E46="",F46=""),"",E46*F46/1000000*IF(H46="",1,H46)) | O46: =IF(OR(E46="",F46=""),"",MAX(INT(LISTS!$F$6/(E46+LISTS!$F$8))*INT(LISTS!$F$7/(F46+LISTS!$F$8)),INT(LISTS!$F$6/(F46+LISTS!$F$8))*INT(LISTS!$F$7/(E46+LISTS!$F$8)))) | P46: =IF(K46<>"",K46,IF(OR(O46="",O46=0),"",IF(H46="",1,H46)/O46)) | Q46: =IF(OR(K46<>"",P46=""),"",1-(IF(H46="",1,H46)*E46*F46)/(ROUNDUP(P46,0)*LISTS!$F$6*LISTS!$F$7)) | R46: =IF(AND(E46="",K46=""),"",IF(B46="","panel type?",IF(AND(K46="",O46=0),"panel bigger than sheet",IF(AND(G46<>"",ISERROR(FIND("-"&G46,B46))),"T must match panel type",IF(I46="","exposed faces?","OK"))))) | S46: {=IF(OR(B46="",P46=""),"",IFERROR(INDEX(RATES!$C:$C,MATCH(B46,RATES!$A:$A,0)),"rate?"))} | T46: =IF(ISNUMBER(S46),IF(K46<>"",K46,IF(Q46>RATES!$C$97,P46*(1+RATES!$C$98),ROUNDUP(P46,0)))*S46,"")
A47: 2 | M47: =IF(OR(E47="",F47="",G47=""),"",E47*F47*G47/1000000000*IF(H47="",1,H47)) | N47: =IF(OR(E47="",F47=""),"",E47*F47/1000000*IF(H47="",1,H47)) | O47: =IF(OR(E47="",F47=""),"",MAX(INT(LISTS!$F$6/(E47+LISTS!$F$8))*INT(LISTS!$F$7/(F47+LISTS!$F$8)),INT(LISTS!$F$6/(F47+LISTS!$F$8))*INT(LISTS!$F$7/(E47+LISTS!$F$8)))) | P47: =IF(K47<>"",K47,IF(OR(O47="",O47=0),"",IF(H47="",1,H47)/O47)) | Q47: =IF(OR(K47<>"",P47=""),"",1-(IF(H47="",1,H47)*E47*F47)/(ROUNDUP(P47,0)*LISTS!$F$6*LISTS!$F$7)) | R47: =IF(AND(E47="",K47=""),"",IF(B47="","panel type?",IF(AND(K47="",O47=0),"panel bigger than sheet",IF(AND(G47<>"",ISERROR(FIND("-"&G47,B47))),"T must match panel type",IF(I47="","exposed faces?","OK"))))) | S47: {=IF(OR(B47="",P47=""),"",IFERROR(INDEX(RATES!$C:$C,MATCH(B47,RATES!$A:$A,0)),"rate?"))} | T47: =IF(ISNUMBER(S47),IF(K47<>"",K47,IF(Q47>RATES!$C$97,P47*(1+RATES!$C$98),ROUNDUP(P47,0)))*S47,"")
A48: 3 | M48: =IF(OR(E48="",F48="",G48=""),"",E48*F48*G48/1000000000*IF(H48="",1,H48)) | N48: =IF(OR(E48="",F48=""),"",E48*F48/1000000*IF(H48="",1,H48)) | O48: =IF(OR(E48="",F48=""),"",MAX(INT(LISTS!$F$6/(E48+LISTS!$F$8))*INT(LISTS!$F$7/(F48+LISTS!$F$8)),INT(LISTS!$F$6/(F48+LISTS!$F$8))*INT(LISTS!$F$7/(E48+LISTS!$F$8)))) | P48: =IF(K48<>"",K48,IF(OR(O48="",O48=0),"",IF(H48="",1,H48)/O48)) | Q48: =IF(OR(K48<>"",P48=""),"",1-(IF(H48="",1,H48)*E48*F48)/(ROUNDUP(P48,0)*LISTS!$F$6*LISTS!$F$7)) | R48: =IF(AND(E48="",K48=""),"",IF(B48="","panel type?",IF(AND(K48="",O48=0),"panel bigger than sheet",IF(AND(G48<>"",ISERROR(FIND("-"&G48,B48))),"T must match panel type",IF(I48="","exposed faces?","OK"))))) | S48: {=IF(OR(B48="",P48=""),"",IFERROR(INDEX(RATES!$C:$C,MATCH(B48,RATES!$A:$A,0)),"rate?"))} | T48: =IF(ISNUMBER(S48),IF(K48<>"",K48,IF(Q48>RATES!$C$97,P48*(1+RATES!$C$98),ROUNDUP(P48,0)))*S48,"")
A49: 4 | M49: =IF(OR(E49="",F49="",G49=""),"",E49*F49*G49/1000000000*IF(H49="",1,H49)) | N49: =IF(OR(E49="",F49=""),"",E49*F49/1000000*IF(H49="",1,H49)) | O49: =IF(OR(E49="",F49=""),"",MAX(INT(LISTS!$F$6/(E49+LISTS!$F$8))*INT(LISTS!$F$7/(F49+LISTS!$F$8)),INT(LISTS!$F$6/(F49+LISTS!$F$8))*INT(LISTS!$F$7/(E49+LISTS!$F$8)))) | P49: =IF(K49<>"",K49,IF(OR(O49="",O49=0),"",IF(H49="",1,H49)/O49)) | Q49: =IF(OR(K49<>"",P49=""),"",1-(IF(H49="",1,H49)*E49*F49)/(ROUNDUP(P49,0)*LISTS!$F$6*LISTS!$F$7)) | R49: =IF(AND(E49="",K49=""),"",IF(B49="","panel type?",IF(AND(K49="",O49=0),"panel bigger than sheet",IF(AND(G49<>"",ISERROR(FIND("-"&G49,B49))),"T must match panel type",IF(I49="","exposed faces?","OK"))))) | S49: {=IF(OR(B49="",P49=""),"",IFERROR(INDEX(RATES!$C:$C,MATCH(B49,RATES!$A:$A,0)),"rate?"))} | T49: =IF(ISNUMBER(S49),IF(K49<>"",K49,IF(Q49>RATES!$C$97,P49*(1+RATES!$C$98),ROUNDUP(P49,0)))*S49,"")
A50: 5 | M50: =IF(OR(E50="",F50="",G50=""),"",E50*F50*G50/1000000000*IF(H50="",1,H50)) | N50: =IF(OR(E50="",F50=""),"",E50*F50/1000000*IF(H50="",1,H50)) | O50: =IF(OR(E50="",F50=""),"",MAX(INT(LISTS!$F$6/(E50+LISTS!$F$8))*INT(LISTS!$F$7/(F50+LISTS!$F$8)),INT(LISTS!$F$6/(F50+LISTS!$F$8))*INT(LISTS!$F$7/(E50+LISTS!$F$8)))) | P50: =IF(K50<>"",K50,IF(OR(O50="",O50=0),"",IF(H50="",1,H50)/O50)) | Q50: =IF(OR(K50<>"",P50=""),"",1-(IF(H50="",1,H50)*E50*F50)/(ROUNDUP(P50,0)*LISTS!$F$6*LISTS!$F$7)) | R50: =IF(AND(E50="",K50=""),"",IF(B50="","panel type?",IF(AND(K50="",O50=0),"panel bigger than sheet",IF(AND(G50<>"",ISERROR(FIND("-"&G50,B50))),"T must match panel type",IF(I50="","exposed faces?","OK"))))) | S50: {=IF(OR(B50="",P50=""),"",IFERROR(INDEX(RATES!$C:$C,MATCH(B50,RATES!$A:$A,0)),"rate?"))} | T50: =IF(ISNUMBER(S50),IF(K50<>"",K50,IF(Q50>RATES!$C$97,P50*(1+RATES!$C$98),ROUNDUP(P50,0)))*S50,"")
A51: 6 | M51: =IF(OR(E51="",F51="",G51=""),"",E51*F51*G51/1000000000*IF(H51="",1,H51)) | N51: =IF(OR(E51="",F51=""),"",E51*F51/1000000*IF(H51="",1,H51)) | O51: =IF(OR(E51="",F51=""),"",MAX(INT(LISTS!$F$6/(E51+LISTS!$F$8))*INT(LISTS!$F$7/(F51+LISTS!$F$8)),INT(LISTS!$F$6/(F51+LISTS!$F$8))*INT(LISTS!$F$7/(E51+LISTS!$F$8)))) | P51: =IF(K51<>"",K51,IF(OR(O51="",O51=0),"",IF(H51="",1,H51)/O51)) | Q51: =IF(OR(K51<>"",P51=""),"",1-(IF(H51="",1,H51)*E51*F51)/(ROUNDUP(P51,0)*LISTS!$F$6*LISTS!$F$7)) | R51: =IF(AND(E51="",K51=""),"",IF(B51="","panel type?",IF(AND(K51="",O51=0),"panel bigger than sheet",IF(AND(G51<>"",ISERROR(FIND("-"&G51,B51))),"T must match panel type",IF(I51="","exposed faces?","OK"))))) | S51: {=IF(OR(B51="",P51=""),"",IFERROR(INDEX(RATES!$C:$C,MATCH(B51,RATES!$A:$A,0)),"rate?"))} | T51: =IF(ISNUMBER(S51),IF(K51<>"",K51,IF(Q51>RATES!$C$97,P51*(1+RATES!$C$98),ROUNDUP(P51,0)))*S51,"")
A52: 7 | M52: =IF(OR(E52="",F52="",G52=""),"",E52*F52*G52/1000000000*IF(H52="",1,H52)) | N52: =IF(OR(E52="",F52=""),"",E52*F52/1000000*IF(H52="",1,H52)) | O52: =IF(OR(E52="",F52=""),"",MAX(INT(LISTS!$F$6/(E52+LISTS!$F$8))*INT(LISTS!$F$7/(F52+LISTS!$F$8)),INT(LISTS!$F$6/(F52+LISTS!$F$8))*INT(LISTS!$F$7/(E52+LISTS!$F$8)))) | P52: =IF(K52<>"",K52,IF(OR(O52="",O52=0),"",IF(H52="",1,H52)/O52)) | Q52: =IF(OR(K52<>"",P52=""),"",1-(IF(H52="",1,H52)*E52*F52)/(ROUNDUP(P52,0)*LISTS!$F$6*LISTS!$F$7)) | R52: =IF(AND(E52="",K52=""),"",IF(B52="","panel type?",IF(AND(K52="",O52=0),"panel bigger than sheet",IF(AND(G52<>"",ISERROR(FIND("-"&G52,B52))),"T must match panel type",IF(I52="","exposed faces?","OK"))))) | S52: {=IF(OR(B52="",P52=""),"",IFERROR(INDEX(RATES!$C:$C,MATCH(B52,RATES!$A:$A,0)),"rate?"))} | T52: =IF(ISNUMBER(S52),IF(K52<>"",K52,IF(Q52>RATES!$C$97,P52*(1+RATES!$C$98),ROUNDUP(P52,0)))*S52,"")
A53: 8 | M53: =IF(OR(E53="",F53="",G53=""),"",E53*F53*G53/1000000000*IF(H53="",1,H53)) | N53: =IF(OR(E53="",F53=""),"",E53*F53/1000000*IF(H53="",1,H53)) | O53: =IF(OR(E53="",F53=""),"",MAX(INT(LISTS!$F$6/(E53+LISTS!$F$8))*INT(LISTS!$F$7/(F53+LISTS!$F$8)),INT(LISTS!$F$6/(F53+LISTS!$F$8))*INT(LISTS!$F$7/(E53+LISTS!$F$8)))) | P53: =IF(K53<>"",K53,IF(OR(O53="",O53=0),"",IF(H53="",1,H53)/O53)) | Q53: =IF(OR(K53<>"",P53=""),"",1-(IF(H53="",1,H53)*E53*F53)/(ROUNDUP(P53,0)*LISTS!$F$6*LISTS!$F$7)) | R53: =IF(AND(E53="",K53=""),"",IF(B53="","panel type?",IF(AND(K53="",O53=0),"panel bigger than sheet",IF(AND(G53<>"",ISERROR(FIND("-"&G53,B53))),"T must match panel type",IF(I53="","exposed faces?","OK"))))) | S53: {=IF(OR(B53="",P53=""),"",IFERROR(INDEX(RATES!$C:$C,MATCH(B53,RATES!$A:$A,0)),"rate?"))} | T53: =IF(ISNUMBER(S53),IF(K53<>"",K53,IF(Q53>RATES!$C$97,P53*(1+RATES!$C$98),ROUNDUP(P53,0)))*S53,"")
A54: 9 | M54: =IF(OR(E54="",F54="",G54=""),"",E54*F54*G54/1000000000*IF(H54="",1,H54)) | N54: =IF(OR(E54="",F54=""),"",E54*F54/1000000*IF(H54="",1,H54)) | O54: =IF(OR(E54="",F54=""),"",MAX(INT(LISTS!$F$6/(E54+LISTS!$F$8))*INT(LISTS!$F$7/(F54+LISTS!$F$8)),INT(LISTS!$F$6/(F54+LISTS!$F$8))*INT(LISTS!$F$7/(E54+LISTS!$F$8)))) | P54: =IF(K54<>"",K54,IF(OR(O54="",O54=0),"",IF(H54="",1,H54)/O54)) | Q54: =IF(OR(K54<>"",P54=""),"",1-(IF(H54="",1,H54)*E54*F54)/(ROUNDUP(P54,0)*LISTS!$F$6*LISTS!$F$7)) | R54: =IF(AND(E54="",K54=""),"",IF(B54="","panel type?",IF(AND(K54="",O54=0),"panel bigger than sheet",IF(AND(G54<>"",ISERROR(FIND("-"&G54,B54))),"T must match panel type",IF(I54="","exposed faces?","OK"))))) | S54: {=IF(OR(B54="",P54=""),"",IFERROR(INDEX(RATES!$C:$C,MATCH(B54,RATES!$A:$A,0)),"rate?"))} | T54: =IF(ISNUMBER(S54),IF(K54<>"",K54,IF(Q54>RATES!$C$97,P54*(1+RATES!$C$98),ROUNDUP(P54,0)))*S54,"")
A55: 10 | M55: =IF(OR(E55="",F55="",G55=""),"",E55*F55*G55/1000000000*IF(H55="",1,H55)) | N55: =IF(OR(E55="",F55=""),"",E55*F55/1000000*IF(H55="",1,H55)) | O55: =IF(OR(E55="",F55=""),"",MAX(INT(LISTS!$F$6/(E55+LISTS!$F$8))*INT(LISTS!$F$7/(F55+LISTS!$F$8)),INT(LISTS!$F$6/(F55+LISTS!$F$8))*INT(LISTS!$F$7/(E55+LISTS!$F$8)))) | P55: =IF(K55<>"",K55,IF(OR(O55="",O55=0),"",IF(H55="",1,H55)/O55)) | Q55: =IF(OR(K55<>"",P55=""),"",1-(IF(H55="",1,H55)*E55*F55)/(ROUNDUP(P55,0)*LISTS!$F$6*LISTS!$F$7)) | R55: =IF(AND(E55="",K55=""),"",IF(B55="","panel type?",IF(AND(K55="",O55=0),"panel bigger than sheet",IF(AND(G55<>"",ISERROR(FIND("-"&G55,B55))),"T must match panel type",IF(I55="","exposed faces?","OK"))))) | S55: {=IF(OR(B55="",P55=""),"",IFERROR(INDEX(RATES!$C:$C,MATCH(B55,RATES!$A:$A,0)),"rate?"))} | T55: =IF(ISNUMBER(S55),IF(K55<>"",K55,IF(Q55>RATES!$C$97,P55*(1+RATES!$C$98),ROUNDUP(P55,0)))*S55,"")
A56: 11 | M56: =IF(OR(E56="",F56="",G56=""),"",E56*F56*G56/1000000000*IF(H56="",1,H56)) | N56: =IF(OR(E56="",F56=""),"",E56*F56/1000000*IF(H56="",1,H56)) | O56: =IF(OR(E56="",F56=""),"",MAX(INT(LISTS!$F$6/(E56+LISTS!$F$8))*INT(LISTS!$F$7/(F56+LISTS!$F$8)),INT(LISTS!$F$6/(F56+LISTS!$F$8))*INT(LISTS!$F$7/(E56+LISTS!$F$8)))) | P56: =IF(K56<>"",K56,IF(OR(O56="",O56=0),"",IF(H56="",1,H56)/O56)) | Q56: =IF(OR(K56<>"",P56=""),"",1-(IF(H56="",1,H56)*E56*F56)/(ROUNDUP(P56,0)*LISTS!$F$6*LISTS!$F$7)) | R56: =IF(AND(E56="",K56=""),"",IF(B56="","panel type?",IF(AND(K56="",O56=0),"panel bigger than sheet",IF(AND(G56<>"",ISERROR(FIND("-"&G56,B56))),"T must match panel type",IF(I56="","exposed faces?","OK"))))) | S56: {=IF(OR(B56="",P56=""),"",IFERROR(INDEX(RATES!$C:$C,MATCH(B56,RATES!$A:$A,0)),"rate?"))} | T56: =IF(ISNUMBER(S56),IF(K56<>"",K56,IF(Q56>RATES!$C$97,P56*(1+RATES!$C$98),ROUNDUP(P56,0)))*S56,"")
A57: 12 | M57: =IF(OR(E57="",F57="",G57=""),"",E57*F57*G57/1000000000*IF(H57="",1,H57)) | N57: =IF(OR(E57="",F57=""),"",E57*F57/1000000*IF(H57="",1,H57)) | O57: =IF(OR(E57="",F57=""),"",MAX(INT(LISTS!$F$6/(E57+LISTS!$F$8))*INT(LISTS!$F$7/(F57+LISTS!$F$8)),INT(LISTS!$F$6/(F57+LISTS!$F$8))*INT(LISTS!$F$7/(E57+LISTS!$F$8)))) | P57: =IF(K57<>"",K57,IF(OR(O57="",O57=0),"",IF(H57="",1,H57)/O57)) | Q57: =IF(OR(K57<>"",P57=""),"",1-(IF(H57="",1,H57)*E57*F57)/(ROUNDUP(P57,0)*LISTS!$F$6*LISTS!$F$7)) | R57: =IF(AND(E57="",K57=""),"",IF(B57="","panel type?",IF(AND(K57="",O57=0),"panel bigger than sheet",IF(AND(G57<>"",ISERROR(FIND("-"&G57,B57))),"T must match panel type",IF(I57="","exposed faces?","OK"))))) | S57: {=IF(OR(B57="",P57=""),"",IFERROR(INDEX(RATES!$C:$C,MATCH(B57,RATES!$A:$A,0)),"rate?"))} | T57: =IF(ISNUMBER(S57),IF(K57<>"",K57,IF(Q57>RATES!$C$97,P57*(1+RATES!$C$98),ROUNDUP(P57,0)))*S57,"")
... A60: 15 | M60: =IF(OR(E60="",F60="",G60=""),"",E60*F60*G60/1000000000*IF(H60="",1,H60)) | N60: =IF(OR(E60="",F60=""),"",E60*F60/1000000*IF(H60="",1,H60)) | O60: =IF(OR(E60="",F60=""),"",MAX(INT(LISTS!$F$6/(E60+LISTS!$F$8))*INT(LISTS!$F$7/(F60+LISTS!$F$8)),INT(LISTS!$F$6/(F60+LISTS!$F$8))*INT(LISTS!$F$7/(E60+LISTS!$F$8)))) | P60: =IF(K60<>"",K60,IF(OR(O60="",O60=0),"",IF(H60="",1,H60)/O60)) | Q60: =IF(OR(K60<>"",P60=""),"",1-(IF(H60="",1,H60)*E60*F60)/(ROUNDUP(P60,0)*LISTS!$F$6*LISTS!$F$7)) | R60: =IF(AND(E60="",K60=""),"",IF(B60="","panel type?",IF(AND(K60="",O60=0),"panel bigger than sheet",IF(AND(G60<>"",ISERROR(FIND("-"&G60,B60))),"T must match panel type",IF(I60="","exposed faces?","OK"))))) | S60: {=IF(OR(B60="",P60=""),"",IFERROR(INDEX(RATES!$C:$C,MATCH(B60,RATES!$A:$A,0)),"rate?"))} | T60: =IF(ISNUMBER(S60),IF(K60<>"",K60,IF(Q60>RATES!$C$97,P60*(1+RATES!$C$98),ROUNDUP(P60,0)))*S60,"")
A62: HARDWARE & BOUGHT-IN: runners, hinges, handles, metal frames, rattan, glass, mirror, fabric, foam, outside labour. ENTER UNIT PRICE IDR.
A63: NO | B63: ITEM MASTER CODE | C63: LABEL | D63: DESCRIPTION | E63: VENDOR | H63: QTY | I63: UOM | L63: LINK / NOTE | S63: UNIT PRICE IDR | T63: LINE TOTAL (calc) | U63: LINE TOTAL USD
A64: 1 | T64: =IF(OR(H64="",S64=""),"",H64*S64)
A65: 2 | T65: =IF(OR(H65="",S65=""),"",H65*S65)
A66: 3 | T66: =IF(OR(H66="",S66=""),"",H66*S66)
A67: 4 | T67: =IF(OR(H67="",S67=""),"",H67*S67)
A68: 5 | T68: =IF(OR(H68="",S68=""),"",H68*S68)
A69: 6 | T69: =IF(OR(H69="",S69=""),"",H69*S69)
A70: 7 | T70: =IF(OR(H70="",S70=""),"",H70*S70)
A71: 8 | T71: =IF(OR(H71="",S71=""),"",H71*S71)
A72: 9 | T72: =IF(OR(H72="",S72=""),"",H72*S72)
A73: 10 | T73: =IF(OR(H73="",S73=""),"",H73*S73)
A74: 11 | T74: =IF(OR(H74="",S74=""),"",H74*S74)
A75: 12 | T75: =IF(OR(H75="",S75=""),"",H75*S75)
... A78: 15 | T78: =IF(OR(H78="",S78=""),"",H78*S78)
C80: METAL (hollow, per m) | D80: =SUM(T35:T42) | F80: Σ length m × IDR/m of the hollow code (RATES list)
A81: SUMMARY (system): cost per ONE item, from the RATES tab. Do not type here. | E81: COST USD (system)
C82: Solid wood m³ | D82: =SUM(M18:M32)
C83: Panel sheets | D83: =SUM(P46:P60)
C84: Finishing m² (exposed) | D84: =SUMIF(I18:I32,"Y",N18:N32)+SUMIF(I35:I42,"Y",N35:N42)+SUMIF(I46:I60,1,N46:N60)+2*SUMIF(I46:I60,2,N46:N60) | F84: one face (L × W) per exposed solid component + exposed panel faces
C85: Cartons | D85: =G15
C86: Carton m³ | D86: =M15
C87: TIMBER | D87: =SUM(T18:T32) | F87: Σ component m³ × tier rate (yield, processing and carpentry labour inside)
C88: FASTENERS | D88: =D82*RATES!$C$46 | F88: solid wood m³ × FASTENERS
C89: PANELS | D89: =SUM(T46:T60) | F89: sheets charged × sheet rate (nested, or manual sheets)
C90: FINISHING MATERIALS | D90: =D84*RATES!$C$47*IF($C$5="NONE (RAW)",0,1) | F90: exposed m² × FIN_MAT (Zhanchen + thinner). All four finishing lines = 0 when FINISH RECIPE is NONE (RAW)
C91: SANDING MATERIALS | D91: =D84*RATES!$C$48*IF($C$5="NONE (RAW)",0,1) | F91: exposed m² × SAND_MAT (abrasives)
C92: SANDING LABOUR | D92: =D84*RATES!$C$49*IF($C$5="NONE (RAW)",0,1) | F92: exposed m² × SAND_LAB
C93: FINISHING LABOUR | D93: =D84*RATES!$C$50*IF($C$5="NONE (RAW)",0,1) | F93: exposed m² × FIN_LAB
C94: HARDWARE | D94: =SUM(T64:T78) | F94: Σ hardware & bought-in lines (qty × unit price entered by the team)
C95: PACKING | D95: =IF(L15=0,0,IF(L15<RATES!$C$95,RATES!$C$53*G15,L15*RATES!$C$51*(1+IF(G15>1,RATES!$C$96,0)))+M15*RATES!$C$52) | F95: carton m² × CARTON_M2 + carton m³ × PACK_LAB
C96: TOTAL COST | D96: =SUM(D87:D95) | F96: Σ of the nine lines above
C97: MISC 4% | D97: =D96*RATES!$C$54 | F97: total cost × MISC_PCT
C98: DIRECT COST IDR (HPP) | D98: =D96+D97 | F98: total cost + misc
B99: =RATES!$C$169 | C99: DIRECT COST USD | D99: =D98/RATES!$C$169 | F99: HPP ÷ FX_TARGET (IDR/USD in column B)
C100: TARGET PRICE USD | D100: =D99*RATES!$C$55 | F100: direct cost USD × TARGET_X
C101: ORDER QTY × DIRECT COST IDR | D101: =IF(ISNUMBER(C4),C4,0)*D98
C102: Open input checks | D102: =COUNTIF(R18:R32,"?*")-COUNTIF(R18:R32,"OK")+COUNTIF(R35:R42,"?*")-COUNTIF(R35:R42,"OK")+COUNTIF(R46:R60,"?*")-COUNTIF(R46:R60,"OK")+COUNTIF(S18:S60,"rate?") | F102: must be 0 before the item counts as costed (see CHECK column)

Sheet RATES
A1: RATES: PLV BOM Rate Card 29 Sep 26 (rates_version 2026-09-29), with the 30 Sep changes: finishing split into four rates, 40 × 40 section rule
A2: Blue = base figure (change it and every cost in this workbook follows). Black = formula. Item tabs look rates up by the code in column A. Only the rate owner edits this tab.
A3: Same rate card as the PLV BOM Costing Workbook v3 (teak, mindi, meranti, plywood). Plywood keeps the Mojo Indah Sep 2026 rates; columns F and G show the Linyi Ocean landed quote of 16 Oct 2026 in USD and IDR for comparison. MDF, marine plywood (rows 170 onward) and DTC rails and hinges (rows 227–229) are priced from USD. Orange rows = rate with both a USD and an IDR price. No rates yet for oak / ash, oak veneer, rattan or metal frames.
A4: code | B4: Description | C4: Value | D4: Unit | E4: Source | F4: Quote USD (Linyi Ocean landed, 16 Oct 2026) | G4: Quote IDR (USD × FX_USD)
A5: BASE FIGURES: STMV (Standard Maldives) ledger, payroll and vendor lists
A6: log_teak | B6: Teak log price, implied | C6: 6000000 | D6: IDR/m³ | E6: Ledger 152.3m ÷ 14 m³. Status CONFIRM: replace with nota price
A7: log_mindi | B7: Mindi log price, implied | C7: 3000000 | D7: IDR/m³ | E7: Ledger 126.1m ÷ 41 m³. Status CONFIRM
A8: meranti_sawn | B8: Meranti dry sawn timber | C8: 8500000 | D8: IDR/m³ | E8: STMV BOM price. Status CONFIRM
A9: processing | B9: Wood processing (kiln + sawmill + hauling + sawmill staff), per m³ of log | C9: 598978 | D9: IDR/m³ | E9: Ledger ÷ 75.82 m³ teak + mindi
A10: carp_pool | B10: Carpentry payroll pool Mar–Sep 2026 | C10: 270175017 | D10: IDR | E10: Payroll categorised by name, 29 Sep
A11: carp_deduct | B11: Less panel cutting / pressing (already in panel rate) | C11: 0.1 | D11: % | E11: Decision 29 Sep
A12: comp_m3 | B12: STMV solid wood in components (teak 12.21 + mindi 13.15 + meranti 7.20) | C12: 32.56 | D12: m³ | E12: REVISI BOM 21 MEI 26
A13: yield_A | B13: Yield factor tier A (exposed, straight, ≥ 1000 mm) | C13: 3.5 | D13: x | E13: Judgement, open item
A14: yield_AC | B14: Yield factor tier A-CURVED / wide board | C14: 4.6 | D14: x | E14: STMV mindi
A15: yield_B | B15: Yield factor tier B (exposed < 1000 mm, or section ≤ 40 × 40 up to 1500 mm) | C15: 2.5 | D15: x | E15: Judgement, open item
A16: yield_C | B16: Yield factor tier C (not exposed) | C16: 2 | D16: x | E16: STMV teak
A17: yield_D | B17: Yield factor tier D (very small parts) | C17: 1.5 | D17: x | E17: Judgement, open item
... A32: ven_labour | B32: Pressing labour per face (tape, press, sand, cut) | C32: 57142.86 | D32: IDR/face | E32: 800,000 ÷ 14 sheets. Status CONFIRM
A33: RATE CARD: applied by the item tabs
A34: LAB_CARP | B34: Carpentry labour per m³ of component (inside every tier rate) | C34: 4000000 | D34: IDR/m³ | E34: Pool less 10% ÷ component m³
A35: TEAK_A | B35: Teak tier A | C35: 27507965 | D35: IDR/m³ | E35: (log + processing) × yield + labour
A36: TEAK_AC | B36: Teak tier A-CURVED | C36: 34040953 | D36: IDR/m³
A37: TEAK_B | B37: Teak tier B | C37: 21568885 | D37: IDR/m³
A38: TEAK_C | B38: Teak tier C | C38: 18599345 | D38: IDR/m³
A39: TEAK_D | B39: Teak tier D | C39: 15629805 | D39: IDR/m³
A40: MINDI_A | B40: Mindi tier A | C40: 11918257 | D40: IDR/m³
A41: MINDI_AC | B41: Mindi tier A-CURVED | C41: 14269829 | D41: IDR/m³
A42: MINDI_B | B42: Mindi tier B | C42: 9780464 | D42: IDR/m³
A43: MINDI_C | B43: Mindi tier C | C43: 8711567.6 | D43: IDR/m³
A44: MINDI_D | B44: Mindi tier D | C44: 7642671.1 | D44: IDR/m³
A45: MERANTI | B45: Meranti, any tier | C45: 18196184 | D45: IDR/m³ | E45: Sawn price × yield + labour, no processing
A46: FASTENERS | B46: Screws, nails, dowels, glue per m³ of component | C46: 1000000 | D46: IDR/m³
A47: FIN_MAT | B47: Finishing materials (Zhanchen + thinner) per m² exposed | C47: 37000 | D47: IDR/m²
A48: SAND_MAT | B48: Sanding materials (abrasives) per m² exposed | C48: 10235.642 | D48: IDR/m²
A49: SAND_LAB | B49: Sanding labour (65% of sanding pool) per m² exposed | C49: 20000 | D49: IDR/m²
A50: FIN_LAB | B50: Finishing labour (finishing pool) per m² exposed | C50: 45000 | D50: IDR/m²
A51: CARTON_M2 | B51: Carton + consumables per m² of carton board (6 sides) | C51: 40000 | D51: IDR/m² | E51: Cartons 59.4m + 40% of other packing materials
A52: PACK_LAB | B52: Packing labour per m³ of carton | C52: 50000 | D52: IDR/m³ | E52: 6 people × 8 days per container. Status CONFIRM
A53: GRP_A | B53: Carton group A price (boxes under CARTON_MIN_M2) | C53: 24000 | D53: IDR | E53: STMV carton groups, 28 Sep
A54: MISC_PCT | B54: Miscellaneous, × direct cost | C54: 0.04 | D54: % | E54: Rizky 23 Okt 2026: 4% of TOTAL COST (was 5%)
A55: TARGET_X | B55: Target price = DIRECT COST in USD x this factor | C55: 1.5 | D55: x | E55: Rizky 23 Okt 2026 (replaces OH_PCT, deleted). Blue = input
A56: PLYWOOD per 2440 × 1220 sheet. RAW = board only; MSF / MDF = mindi veneer 1 / 2 faces; TSF / TDF = teak veneer 1 / 2 faces
A57: VEN_TEAK_FACE | B57: Teak veneer added cost per face (veneer + glue/tape + pressing labour) | C57: =$C$29*$C$31+$C$28*(LISTS!$F$6*LISTS!$F$7/1000000)+$C$32 | D57: IDR/face
A58: VEN_MINDI_FACE | B58: Mindi veneer added cost per face | C58: 18000 | D58: m2
A59: PLY-3-RAW | B59: Plywood 3 mm, raw | C59: =G59 | D59: IDR/sheet | E59: E2 landed Kudus (Linyi quote 16 Oct 2026). Grade LOCKED E2 | F59: {=INDEX($F$178:$F$215,MATCH("LND-PLY-"&$C$174&"-3",$A$178:$A$215,0))} | G59: =F59*$C$172
A60: PLY-3-MSF | B60: Plywood 3 mm, mindi single face | C60: =C59+$C$175 | D60: IDR/sheet
A61: PLY-3-MDF | B61: Plywood 3 mm, mindi double face | C61: =C59+2*$C$175 | D61: IDR/sheet
A62: PLY-3-TSF | B62: Plywood 3 mm, teak single face | C62: =C59+$C$176 | D62: IDR/sheet
A63: PLY-3-TDF | B63: Plywood 3 mm, teak double face | C63: =C59+2*$C$176 | D63: IDR/sheet
A64: PLY-6-RAW | B64: Plywood 6 mm, raw | C64: =G64 | D64: IDR/sheet | E64: E2 landed Kudus (Linyi quote 16 Oct 2026). Grade LOCKED E2 | F64: {=INDEX($F$178:$F$215,MATCH("LND-PLY-"&$C$174&"-6",$A$178:$A$215,0))} | G64: =F64*$C$172
A65: PLY-6-MSF | B65: Plywood 6 mm, mindi single face | C65: =C64+$C$175 | D65: IDR/sheet
A66: PLY-6-MDF | B66: Plywood 6 mm, mindi double face | C66: =C64+2*$C$175 | D66: IDR/sheet
A67: PLY-6-TSF | B67: Plywood 6 mm, teak single face | C67: =C64+$C$176 | D67: IDR/sheet
A68: PLY-6-TDF | B68: Plywood 6 mm, teak double face | C68: =C64+2*$C$176 | D68: IDR/sheet
A69: PLY-9-RAW | B69: Plywood 9 mm, raw | C69: =G69 | D69: IDR/sheet | E69: E2 landed Kudus (Linyi quote 16 Oct 2026). Grade LOCKED E2 | F69: {=INDEX($F$178:$F$215,MATCH("LND-PLY-"&$C$174&"-9",$A$178:$A$215,0))} | G69: =F69*$C$172
A70: PLY-9-MSF | B70: Plywood 9 mm, mindi single face | C70: =C69+$C$175 | D70: IDR/sheet
A71: PLY-9-MDF | B71: Plywood 9 mm, mindi double face | C71: =C69+2*$C$175 | D71: IDR/sheet
A72: PLY-9-TSF | B72: Plywood 9 mm, teak single face | C72: =C69+$C$176 | D72: IDR/sheet
A73: PLY-9-TDF | B73: Plywood 9 mm, teak double face | C73: =C69+2*$C$176 | D73: IDR/sheet
A74: PLY-12-RAW | B74: Plywood 12 mm, raw | C74: =G74 | D74: IDR/sheet | E74: E2 landed Kudus (Linyi quote 16 Oct 2026). Grade LOCKED E2 | F74: {=INDEX($F$178:$F$215,MATCH("LND-PLY-"&$C$174&"-12",$A$178:$A$215,0))} | G74: =F74*$C$172
A75: PLY-12-MSF | B75: Plywood 12 mm, mindi single face | C75: =C74+$C$175 | D75: IDR/sheet
A76: PLY-12-MDF | B76: Plywood 12 mm, mindi double face | C76: =C74+2*$C$175 | D76: IDR/sheet
A77: PLY-12-TSF | B77: Plywood 12 mm, teak single face | C77: =C74+$C$176 | D77: IDR/sheet
A78: PLY-12-TDF | B78: Plywood 12 mm, teak double face | C78: =C74+2*$C$176 | D78: IDR/sheet
A79: PLY-15-RAW | B79: Plywood 15 mm, raw | C79: 260000 | D79: IDR/sheet | E79: E2 landed Kudus (Linyi quote 16 Oct 2026). Grade LOCKED E2 | F79: {=INDEX($F$178:$F$215,MATCH("LND-PLY-"&$C$174&"-15",$A$178:$A$215,0))} | G79: =F79*$C$172
A80: PLY-15-MSF | B80: Plywood 15 mm, mindi single face | C80: 407709.02 | D80: IDR/sheet
A81: PLY-15-MDF | B81: Plywood 15 mm, mindi double face | C81: 555418.04 | D81: IDR/sheet
A82: PLY-15-TSF | B82: Plywood 15 mm, teak single face | C82: 601201.02 | D82: IDR/sheet
A83: PLY-15-TDF | B83: Plywood 15 mm, teak double face | C83: 942402.04 | D83: IDR/sheet
A84: PLY-18-RAW | B84: Plywood 18 mm, raw | C84: =G84 | D84: IDR/sheet | E84: E2 landed Kudus (Linyi quote 16 Oct 2026). Grade LOCKED E2 | F84: {=INDEX($F$178:$F$215,MATCH("LND-PLY-"&$C$174&"-18",$A$178:$A$215,0))} | G84: =F84*$C$172
A85: PLY-18-MSF | B85: Plywood 18 mm, mindi single face | C85: =C84+$C$175 | D85: IDR/sheet
A86: PLY-18-MDF | B86: Plywood 18 mm, mindi double face | C86: =C84+2*$C$175 | D86: IDR/sheet
A87: PLY-18-TSF | B87: Plywood 18 mm, teak single face | C87: =C84+$C$176 | D87: IDR/sheet
A88: PLY-18-TDF | B88: Plywood 18 mm, teak double face | C88: =C84+2*$C$176 | D88: IDR/sheet
A89: PLY-24-RAW | B89: Plywood 24 mm, raw | C89: 375000 | D89: IDR/sheet | E89: Extrapolated. Status CONFIRM
A90: PLY-24-MSF | B90: Plywood 24 mm, mindi single face | C90: 522709.02 | D90: IDR/sheet
A91: PLY-24-MDF | B91: Plywood 24 mm, mindi double face | C91: 670418.04 | D91: IDR/sheet
A92: PLY-24-TSF | B92: Plywood 24 mm, teak single face | C92: 716201.02 | D92: IDR/sheet
A93: PLY-24-TDF | B93: Plywood 24 mm, teak double face | C93: 1057402 | D93: IDR/sheet
A94: NORMS
A95: CARTON_MIN_M2 | B95: Below this carton area use group A price | C95: 0.15 | D95: m²
A96: KD_PACK_FACTOR | B96: Extra consumables factor for flatpack (2+ boxes) | C96: 0 | D96: % | E96: 0 = off
A97: WASTE_REUSE_MIN | B97: Offcut on the last sheet counts as reusable when waste exceeds this | C97: 0.25 | D97: % | E97: Decision 29 Sep
A98: OFFCUT_HANDLING | B98: Handling factor on fractional sheets when the offcut is reused | C98: 0.05 | D98: %
A99: PLY-12-CDF | C99: 718794.04 | D99: IDR/sheet | E99: rate card DB (price list 2026)
A100: PLY-12-CSF | C100: 466897.02 | D100: IDR/sheet | E100: rate card DB (price list 2026)
A101: PLY-12-HDF | C101: 510418.04 | D101: IDR/sheet | E101: rate card DB (price list 2026)
A102: PLY-12-HSF | C102: 362709.02 | D102: IDR/sheet | E102: rate card DB (price list 2026)
A103: PLY-12-ODF | C103: 1016474 | D103: IDR/sheet | E103: rate card DB (price list 2026)
A104: PLY-12-OSF | C104: 615737.02 | D104: IDR/sheet | E104: rate card DB (price list 2026)
A105: PLY-12-SDF | C105: 689026.04 | D105: IDR/sheet | E105: rate card DB (price list 2026)
A106: PLY-12-SSF | C106: 452013.02 | D106: IDR/sheet | E106: rate card DB (price list 2026)
A107: PLY-12-WDF | C107: 1105778 | D107: IDR/sheet | E107: rate card DB (price list 2026)
A108: PLY-12-WSF | C108: 660389.02 | D108: IDR/sheet | E108: rate card DB (price list 2026)
A109: PLY-15-CDF | C109: 763794.04 | D109: IDR/sheet | E109: rate card DB (price list 2026)
A110: PLY-15-CSF | C110: 511897.02 | D110: IDR/sheet | E110: rate card DB (price list 2026)
... A168: PLY-9-WSF | C168: 617889.02 | D168: IDR/sheet | E168: rate card DB (price list 2026)
A169: FX_TARGET | B169: USD rate for the summary USD lines, ITEMS USD columns and target price | C169: 17800 | D169: IDR/USD | E169: Rizky 23 Okt 2026. Hardware/board quotes still use FX_USD (row 172)
A170: LANDED BOARD PRICES: Linyi Consmos Imp.&Exp. Co., Ltd., quotation 14 Oct 2026. CIF Semarang plus port, clearance and trucking to Kudus. Value = CIF USD × FX_USD + LAND_40HC ÷ sheets/box.
A171: code | B171: Description | C171: Value | D171: Unit | E171: Source | F171: Quote USD / sheet (landed Kudus) | G171: Quote IDR / sheet (USD × FX_USD) | H171: CIF USD / sheet | I171: Sheets / 40' HC
...

Sheet LISTS
A1: Dropdown lists and thresholds. Do not rename or move.
A2: SOLID_SPECIES | B2: PANEL_TYPE | C2: FINISH_RECIPE | D2: YN | E2: NORM | F2: VALUE
A3: TEAK | B3: LND-PLY-E0-3 | C3: NC NATURAL | D3: Y | E3: TIER_A_MIN_LEN mm | F3: 1000
A4: MINDI | B4: LND-PLY-E0-6 | C4: PU DUCO | D4: N | E4: TIER_D_MAX_VOL m3 | F4: 0.0005
A5: MERANTI | B5: LND-PLY-E0-9 | C5: NC + GLAZE | E5: TIER_D_MAX_LEN mm | F5: 300
A6: OTHER | B6: LND-PLY-E0-12 | C6: NONE (RAW) | E6: SHEET_L mm | F6: 2440
B7: LND-PLY-E0-15 | C7: OTHER | E7: SHEET_W mm | F7: 1220
B8: LND-PLY-E0-18 | E8: SHEET_KERF mm | F8: 5
B9: LND-MDF-E0-3 | E9: CARTON_ADD mm | F9: 40
B10: LND-MDF-E0-6 | E10: NARROW_MAX_SECTION mm | F10: 40
B11: LND-MDF-E0-9 | E11: NARROW_MAX_LEN mm | F11: 1500
B12: LND-MDF-E0-12
B13: LND-MDF-E0-15
B14: LND-MDF-E0-18
B15: LND-PLY-E0-3-MSF
B16: LND-PLY-E0-3-MSF-V10
B17: LND-PLY-E0-3-MSF-V12
B18: LND-PLY-E0-3-MDF
B19: LND-PLY-E0-3-MDF-V10
B20: LND-PLY-E0-3-MDF-V12
B21: LND-PLY-E0-6-MSF
B22: LND-PLY-E0-6-MSF-V10
B23: LND-PLY-E0-6-MSF-V12
... B86: LND-MDF-E0-18-MDF-V12

Sheet LV453-B61
A1: ITEM CODE | C1: LV453-B61 | D1: OVERALL L mm | G1: {=IFERROR(IF(INDEX(ITEMS!$E$5:$E$120,MATCH($C$1,ITEMS!$C$5:$C$120,0))="","",INDEX(ITEMS!$E$5:$E$120,MATCH($C$1,ITEMS!$C$5:$C$120,0))),"")} | L1: =IF(G6="","photo",_xludf.IMAGE(G6))
A2: ITEM NAME | C2: {=IFERROR(IF(INDEX(ITEMS!$D$5:$D$120,MATCH($C$1,ITEMS!$C$5:$C$120,0))="","",INDEX(ITEMS!$D$5:$D$120,MATCH($C$1,ITEMS!$C$5:$C$120,0))),"")} | D2: OVERALL W mm | G2: {=IFERROR(IF(INDEX(ITEMS!$F$5:$F$120,MATCH($C$1,ITEMS!$C$5:$C$120,0))="","",INDEX(ITEMS!$F$5:$F$120,MATCH($C$1,ITEMS!$C$5:$C$120,0))),"")}
A3: COLLECTION / ROOM | C3: {=IFERROR(INDEX(ITEMS!$B$5:$B$120,MATCH($C$1,ITEMS!$C$5:$C$120,0))&" / "&INDEX(ITEMS!$W$5:$W$120,MATCH($C$1,ITEMS!$C$5:$C$120,0)),"")} | D3: OVERALL H mm | G3: {=IFERROR(IF(INDEX(ITEMS!$G$5:$G$120,MATCH($C$1,ITEMS!$C$5:$C$120,0))="","",INDEX(ITEMS!$G$5:$G$120,MATCH($C$1,ITEMS!$C$5:$C$120,0))),"")}
A4: ORDER QTY | C4: {=IFERROR(IF(INDEX(ITEMS!$H$5:$H$120,MATCH($C$1,ITEMS!$C$5:$C$120,0))="","",INDEX(ITEMS!$H$5:$H$120,MATCH($C$1,ITEMS!$C$5:$C$120,0))),"")} | D4: LV453 - B61 - DRESSER 6 DRAWERS.pdf | G4: {=IFERROR(IF(INDEX(ITEMS!$I$5:$I$120,MATCH($C$1,ITEMS!$C$5:$C$120,0))="","",INDEX(ITEMS!$I$5:$I$120,MATCH($C$1,ITEMS!$C$5:$C$120,0))),"")}
A5: FINISH RECIPE | C5: NC NATURAL | D5: SPEC LINK | G5: {=IFERROR(IF(INDEX(ITEMS!$V$5:$V$120,MATCH($C$1,ITEMS!$C$5:$C$120,0))="","",INDEX(ITEMS!$V$5:$V$120,MATCH($C$1,ITEMS!$C$5:$C$120,0))),"")}
A6: FLATPACK? (Y/N) | C6: N | D6: PHOTO LINK
A7: NOTES | C7: {=IFERROR(IF(INDEX(ITEMS!$X$5:$X$120,MATCH($C$1,ITEMS!$C$5:$C$120,0))="","",INDEX(ITEMS!$X$5:$X$120,MATCH($C$1,ITEMS!$C$5:$C$120,0))),"")} | D7: REVISION / DATE
A9: PACKING: assembled = leave boxes blank (system uses overall size + 40 mm as 1 carton). Flatpack = one row per box.
A10: BOX | B10: CONTENTS | D10: L mm | E10: W mm | F10: H mm | G10: QTY | H10: CARTON L | I10: CARTON W | J10: CARTON H | L10: m² 6 sides (calc) | M10: m³ (calc)
A11: 1 | H11: =IF(D11="","",D11+LISTS!$F$9) | I11: =IF(E11="","",E11+LISTS!$F$9) | J11: =IF(F11="","",F11+LISTS!$F$9) | L11: =IF(H11="","",2*(H11*I11+H11*J11+I11*J11)/1000000*IF(G11="",1,G11)) | M11: =IF(H11="","",H11*I11*J11/1000000000*IF(G11="",1,G11))
A12: 2 | H12: =IF(D12="","",D12+LISTS!$F$9) | I12: =IF(E12="","",E12+LISTS!$F$9) | J12: =IF(F12="","",F12+LISTS!$F$9) | L12: =IF(H12="","",2*(H12*I12+H12*J12+I12*J12)/1000000*IF(G12="",1,G12)) | M12: =IF(H12="","",H12*I12*J12/1000000000*IF(G12="",1,G12))
A13: 3 | H13: =IF(D13="","",D13+LISTS!$F$9) | I13: =IF(E13="","",E13+LISTS!$F$9) | J13: =IF(F13="","",F13+LISTS!$F$9) | L13: =IF(H13="","",2*(H13*I13+H13*J13+I13*J13)/1000000*IF(G13="",1,G13)) | M13: =IF(H13="","",H13*I13*J13/1000000000*IF(G13="",1,G13))
A14: 4 | H14: =IF(D14="","",D14+LISTS!$F$9) | I14: =IF(E14="","",E14+LISTS!$F$9) | J14: =IF(F14="","",F14+LISTS!$F$9) | L14: =IF(H14="","",2*(H14*I14+H14*J14+I14*J14)/1000000*IF(G14="",1,G14)) | M14: =IF(H14="","",H14*I14*J14/1000000000*IF(G14="",1,G14))
A15: TOTAL | G15: =IF(D11="",1,SUM(G11:G14)+COUNTIFS(D11:D14,"<>",G11:G14,"")) | H15: cartons | L15: =IF(D11="",IF(OR(G1="",G2="",G3=""),0,2*((G1+LISTS!$F$9)*(G2+LISTS!$F$9)+(G1+LISTS!$F$9)*(G3+LISTS!$F$9)+(G2+LISTS!$F$9)*(G3+LISTS!$F$9))/1000000),SUM(L11:L14)) | M15: =IF(D11="",IF(OR(G1="",G2="",G3=""),0,(G1+LISTS!$F$9)*(G2+LISTS!$F$9)*(G3+LISTS!$F$9)/1000000000),SUM(M11:M14))
A16: SOLID WOOD: one line per component, mm, qty per ONE item
A17: NO | B17: MATERIAL | C17: LABEL | D17: COMPONENT | E17: L mm | F17: W mm | G17: T mm | H17: QTY | I17: EXPOSED Y/N | J17: CURVED Y/N | K17: TIER OVERRIDE | L17: NOTE | M17: VOL m³ (calc) | N17: FACE m² (calc) | O17: AUTO TIER (calc) | R17: CHECK (calc) | S17: RATE (system) | T17: COST IDR (system)
A18: 1 | B18: MINDI | C18: 3 / A | D18: Tiang Kaki Luar (Corner Posts) | E18: 820 | F18: 45 | G18: 45 | H18: 4 | I18: Y | J18: N | L18: Part 3 / Code A (Solid wood 45x45) | P-01 | M18: =IF(OR(E18="",F18="",G18=""),"",E18*F18*G18/1000000000*IF(H18="",1,H18)) | N18: =IF(OR(E18="",F18=""),"",E18*F18/1000000*IF(H18="",1,H18)) | O18: =IF(E18="","",IF(K18<>"",K18,IF(AND(E18*F18*G18/1000000000<LISTS!$F$4,MAX(E18,F18,G18)<LISTS!$F$5),"D",IF(I18="N","C",IF(J18="Y","A-CURVED",IF(AND(MEDIAN(E18,F18,G18)<=LISTS!$F$10,MAX(E18,F18,G18)<=LISTS!$F$11),"B",IF(MAX(E18,F18,G18)>=LISTS!$F$3,"A","B"))))))) | R18: =IF(E18="","",IF(B18="","material?",IF(OR(F18="",G18=""),"size?",IF(I18="","exposed Y/N?",IF(H18="","qty?",IF(B18="OTHER","OTHER: no rate, price it under hardware","OK")))))) | S18: {=IF(OR(O18="",M18=""),"",IF(B18="MERANTI",RATES!$C$45,IFERROR(INDEX(RATES!$C:$C,MATCH(B18&"_"&SUBSTITUTE(O18,"-CURVED","C"),RATES!$A:$A,0)),"rate?")))} | T18: =IF(ISNUMBER(S18),M18*S18,"")
A19: 2 | B19: MINDI | C19: 3 / A | D19: Tiang Kaki Tengah (Center Posts) | E19: 820 | F19: 45 | G19: 45 | H19: 2 | I19: Y | J19: N | L19: Part 3 / Code A (Solid wood 45x45) | P-02 | M19: =IF(OR(E19="",F19="",G19=""),"",E19*F19*G19/1000000000*IF(H19="",1,H19)) | N19: =IF(OR(E19="",F19=""),"",E19*F19/1000000*IF(H19="",1,H19)) | O19: =IF(E19="","",IF(K19<>"",K19,IF(AND(E19*F19*G19/1000000000<LISTS!$F$4,MAX(E19,F19,G19)<LISTS!$F$5),"D",IF(I19="N","C",IF(J19="Y","A-CURVED",IF(AND(MEDIAN(E19,F19,G19)<=LISTS!$F$10,MAX(E19,F19,G19)<=LISTS!$F$11),"B",IF(MAX(E19,F19,G19)>=LISTS!$F$3,"A","B"))))))) | R19: =IF(E19="","",IF(B19="","material?",IF(OR(F19="",G19=""),"size?",IF(I19="","exposed Y/N?",IF(H19="","qty?",IF(B19="OTHER","OTHER: no rate, price it under hardware","OK")))))) | S19: {=IF(OR(O19="",M19=""),"",IF(B19="MERANTI",RATES!$C$45,IFERROR(INDEX(RATES!$C:$C,MATCH(B19&"_"&SUBSTITUTE(O19,"-CURVED","C"),RATES!$A:$A,0)),"rate?")))} | T19: =IF(ISNUMBER(S19),M19*S19,"")
A20: 3 | B20: MINDI | C20: 14 / A | D20: Rel Depan Atas (Top Front Rail) | E20: 1410 | F20: 45 | G20: 30 | H20: 1 | I20: Y | J20: N | L20: Part 14 / Code A (Solid wood 45x30) | P-03 | M20: =IF(OR(E20="",F20="",G20=""),"",E20*F20*G20/1000000000*IF(H20="",1,H20)) | N20: =IF(OR(E20="",F20=""),"",E20*F20/1000000*IF(H20="",1,H20)) | O20: =IF(E20="","",IF(K20<>"",K20,IF(AND(E20*F20*G20/1000000000<LISTS!$F$4,MAX(E20,F20,G20)<LISTS!$F$5),"D",IF(I20="N","C",IF(J20="Y","A-CURVED",IF(AND(MEDIAN(E20,F20,G20)<=LISTS!$F$10,MAX(E20,F20,G20)<=LISTS!$F$11),"B",IF(MAX(E20,F20,G20)>=LISTS!$F$3,"A","B"))))))) | R20: =IF(E20="","",IF(B20="","material?",IF(OR(F20="",G20=""),"size?",IF(I20="","exposed Y/N?",IF(H20="","qty?",IF(B20="OTHER","OTHER: no rate, price it under hardware","OK")))))) | S20: {=IF(OR(O20="",M20=""),"",IF(B20="MERANTI",RATES!$C$45,IFERROR(INDEX(RATES!$C:$C,MATCH(B20&"_"&SUBSTITUTE(O20,"-CURVED","C"),RATES!$A:$A,0)),"rate?")))} | T20: =IF(ISNUMBER(S20),M20*S20,"")
A21: 4 | B21: MINDI | C21: 18 / A | D21: Rel Sekat Laci Horizontal | E21: 680 | F21: 30 | G21: 30 | H21: 4 | I21: Y | J21: N | L21: Part 18 / Code A (Solid wood 30x30) | P-04 | M21: =IF(OR(E21="",F21="",G21=""),"",E21*F21*G21/1000000000*IF(H21="",1,H21)) | N21: =IF(OR(E21="",F21=""),"",E21*F21/1000000*IF(H21="",1,H21)) | O21: =IF(E21="","",IF(K21<>"",K21,IF(AND(E21*F21*G21/1000000000<LISTS!$F$4,MAX(E21,F21,G21)<LISTS!$F$5),"D",IF(I21="N","C",IF(J21="Y","A-CURVED",IF(AND(MEDIAN(E21,F21,G21)<=LISTS!$F$10,MAX(E21,F21,G21)<=LISTS!$F$11),"B",IF(MAX(E21,F21,G21)>=LISTS!$F$3,"A","B"))))))) | R21: =IF(E21="","",IF(B21="","material?",IF(OR(F21="",G21=""),"size?",IF(I21="","exposed Y/N?",IF(H21="","qty?",IF(B21="OTHER","OTHER: no rate, price it under hardware","OK")))))) | S21: {=IF(OR(O21="",M21=""),"",IF(B21="MERANTI",RATES!$C$45,IFERROR(INDEX(RATES!$C:$C,MATCH(B21&"_"&SUBSTITUTE(O21,"-CURVED","C"),RATES!$A:$A,0)),"rate?")))} | T21: =IF(ISNUMBER(S21),M21*S21,"")
A22: 5 | B22: MINDI | C22: 17 / A | D22: Rel Tengah Vertikal Pembagi | E22: 585 | F22: 45 | G22: 30 | H22: 1 | I22: Y | J22: N | L22: Part 17 / Code A (Solid wood 45x30) | P-05 | M22: =IF(OR(E22="",F22="",G22=""),"",E22*F22*G22/1000000000*IF(H22="",1,H22)) | N22: =IF(OR(E22="",F22=""),"",E22*F22/1000000*IF(H22="",1,H22)) | O22: =IF(E22="","",IF(K22<>"",K22,IF(AND(E22*F22*G22/1000000000<LISTS!$F$4,MAX(E22,F22,G22)<LISTS!$F$5),"D",IF(I22="N","C",IF(J22="Y","A-CURVED",IF(AND(MEDIAN(E22,F22,G22)<=LISTS!$F$10,MAX(E22,F22,G22)<=LISTS!$F$11),"B",IF(MAX(E22,F22,G22)>=LISTS!$F$3,"A","B"))))))) | R22: =IF(E22="","",IF(B22="","material?",IF(OR(F22="",G22=""),"size?",IF(I22="","exposed Y/N?",IF(H22="","qty?",IF(B22="OTHER","OTHER: no rate, price it under hardware","OK")))))) | S22: {=IF(OR(O22="",M22=""),"",IF(B22="MERANTI",RATES!$C$45,IFERROR(INDEX(RATES!$C:$C,MATCH(B22&"_"&SUBSTITUTE(O22,"-CURVED","C"),RATES!$A:$A,0)),"rate?")))} | T22: =IF(ISNUMBER(S22),M22*S22,"")
A23: 6 | B23: MINDI | C23: 1 / A | D23: Rel Bawah Depan (Bottom Apron) | E23: 1410 | F23: 45 | G23: 30 | H23: 1 | I23: Y | J23: N | L23: Part 1 / Code A (Solid wood 45x30) | P-06 | M23: =IF(OR(E23="",F23="",G23=""),"",E23*F23*G23/1000000000*IF(H23="",1,H23)) | N23: =IF(OR(E23="",F23=""),"",E23*F23/1000000*IF(H23="",1,H23)) | O23: =IF(E23="","",IF(K23<>"",K23,IF(AND(E23*F23*G23/1000000000<LISTS!$F$4,MAX(E23,F23,G23)<LISTS!$F$5),"D",IF(I23="N","C",IF(J23="Y","A-CURVED",IF(AND(MEDIAN(E23,F23,G23)<=LISTS!$F$10,MAX(E23,F23,G23)<=LISTS!$F$11),"B",IF(MAX(E23,F23,G23)>=LISTS!$F$3,"A","B"))))))) | R23: =IF(E23="","",IF(B23="","material?",IF(OR(F23="",G23=""),"size?",IF(I23="","exposed Y/N?",IF(H23="","qty?",IF(B23="OTHER","OTHER: no rate, price it under hardware","OK")))))) | S23: {=IF(OR(O23="",M23=""),"",IF(B23="MERANTI",RATES!$C$45,IFERROR(INDEX(RATES!$C:$C,MATCH(B23&"_"&SUBSTITUTE(O23,"-CURVED","C"),RATES!$A:$A,0)),"rate?")))} | T23: =IF(ISNUMBER(S23),M23*S23,"")
A24: 7 | B24: MINDI | C24: 2 / A | D24: Rel Samping (Side Rails) | E24: 360 | F24: 45 | G24: 30 | H24: 4 | I24: Y | J24: N | L24: Part 2 / Code A (Solid wood 45x30) | P-07 | M24: =IF(OR(E24="",F24="",G24=""),"",E24*F24*G24/1000000000*IF(H24="",1,H24)) | N24: =IF(OR(E24="",F24=""),"",E24*F24/1000000*IF(H24="",1,H24)) | O24: =IF(E24="","",IF(K24<>"",K24,IF(AND(E24*F24*G24/1000000000<LISTS!$F$4,MAX(E24,F24,G24)<LISTS!$F$5),"D",IF(I24="N","C",IF(J24="Y","A-CURVED",IF(AND(MEDIAN(E24,F24,G24)<=LISTS!$F$10,MAX(E24,F24,G24)<=LISTS!$F$11),"B",IF(MAX(E24,F24,G24)>=LISTS!$F$3,"A","B"))))))) | R24: =IF(E24="","",IF(B24="","material?",IF(OR(F24="",G24=""),"size?",IF(I24="","exposed Y/N?",IF(H24="","qty?",IF(B24="OTHER","OTHER: no rate, price it under hardware","OK")))))) | S24: {=IF(OR(O24="",M24=""),"",IF(B24="MERANTI",RATES!$C$45,IFERROR(INDEX(RATES!$C:$C,MATCH(B24&"_"&SUBSTITUTE(O24,"-CURVED","C"),RATES!$A:$A,0)),"rate?")))} | T24: =IF(ISNUMBER(S24),M24*S24,"")
A25: 8 | B25: MINDI | C25: 16 / A | D25: Rel Belakang (Rear Rails) | E25: 1410 | F25: 45 | G25: 30 | H25: 2 | I25: N | J25: N | L25: Part 16 / Code A (Solid wood 45x30) | P-08 | M25: =IF(OR(E25="",F25="",G25=""),"",E25*F25*G25/1000000000*IF(H25="",1,H25)) | N25: =IF(OR(E25="",F25=""),"",E25*F25/1000000*IF(H25="",1,H25)) | O25: =IF(E25="","",IF(K25<>"",K25,IF(AND(E25*F25*G25/1000000000<LISTS!$F$4,MAX(E25,F25,G25)<LISTS!$F$5),"D",IF(I25="N","C",IF(J25="Y","A-CURVED",IF(AND(MEDIAN(E25,F25,G25)<=LISTS!$F$10,MAX(E25,F25,G25)<=LISTS!$F$11),"B",IF(MAX(E25,F25,G25)>=LISTS!$F$3,"A","B"))))))) | R25: =IF(E25="","",IF(B25="","material?",IF(OR(F25="",G25=""),"size?",IF(I25="","exposed Y/N?",IF(H25="","qty?",IF(B25="OTHER","OTHER: no rate, price it under hardware","OK")))))) | S25: {=IF(OR(O25="",M25=""),"",IF(B25="MERANTI",RATES!$C$45,IFERROR(INDEX(RATES!$C:$C,MATCH(B25&"_"&SUBSTITUTE(O25,"-CURVED","C"),RATES!$A:$A,0)),"rate?")))} | T25: =IF(ISNUMBER(S25),M25*S25,"")
A26: 9 | B26: MINDI | C26: 6 / A | D26: Frame Muka Laci Stile | E26: 200 | F26: 45 | G26: 20 | H26: 12 | I26: Y | J26: N | L26: Part 6 / Code A (Solid wood 45x20) | P-09 | M26: =IF(OR(E26="",F26="",G26=""),"",E26*F26*G26/1000000000*IF(H26="",1,H26)) | N26: =IF(OR(E26="",F26=""),"",E26*F26/1000000*IF(H26="",1,H26)) | O26: =IF(E26="","",IF(K26<>"",K26,IF(AND(E26*F26*G26/1000000000<LISTS!$F$4,MAX(E26,F26,G26)<LISTS!$F$5),"D",IF(I26="N","C",IF(J26="Y","A-CURVED",IF(AND(MEDIAN(E26,F26,G26)<=LISTS!$F$10,MAX(E26,F26,G26)<=LISTS!$F$11),"B",IF(MAX(E26,F26,G26)>=LISTS!$F$3,"A","B"))))))) | R26: =IF(E26="","",IF(B26="","material?",IF(OR(F26="",G26=""),"size?",IF(I26="","exposed Y/N?",IF(H26="","qty?",IF(B26="OTHER","OTHER: no rate, price it under hardware","OK")))))) | S26: {=IF(OR(O26="",M26=""),"",IF(B26="MERANTI",RATES!$C$45,IFERROR(INDEX(RATES!$C:$C,MATCH(B26&"_"&SUBSTITUTE(O26,"-CURVED","C"),RATES!$A:$A,0)),"rate?")))} | T26: =IF(ISNUMBER(S26),M26*S26,"")
A27: 10 | B27: MINDI | C27: 6 / A | D27: Frame Muka Laci Rail | E27: 615 | F27: 45 | G27: 20 | H27: 12 | I27: Y | J27: N | L27: Part 6 / Code A (Solid wood 45x20) | P-10 | M27: =IF(OR(E27="",F27="",G27=""),"",E27*F27*G27/1000000000*IF(H27="",1,H27)) | N27: =IF(OR(E27="",F27=""),"",E27*F27/1000000*IF(H27="",1,H27)) | O27: =IF(E27="","",IF(K27<>"",K27,IF(AND(E27*F27*G27/1000000000<LISTS!$F$4,MAX(E27,F27,G27)<LISTS!$F$5),"D",IF(I27="N","C",IF(J27="Y","A-CURVED",IF(AND(MEDIAN(E27,F27,G27)<=LISTS!$F$10,MAX(E27,F27,G27)<=LISTS!$F$11),"B",IF(MAX(E27,F27,G27)>=LISTS!$F$3,"A","B"))))))) | R27: =IF(E27="","",IF(B27="","material?",IF(OR(F27="",G27=""),"size?",IF(I27="","exposed Y/N?",IF(H27="","qty?",IF(B27="OTHER","OTHER: no rate, price it under hardware","OK")))))) | S27: {=IF(OR(O27="",M27=""),"",IF(B27="MERANTI",RATES!$C$45,IFERROR(INDEX(RATES!$C:$C,MATCH(B27&"_"&SUBSTITUTE(O27,"-CURVED","C"),RATES!$A:$A,0)),"rate?")))} | T27: =IF(ISNUMBER(S27),M27*S27,"")
A28: 11 | B28: MINDI | C28: 18 / A | D28: Drawer Cleats / Runner Supports | E28: 350 | F28: 30 | G28: 20 | H28: 12 | I28: N | J28: N | L28: Part 18 / Code A (Solid wood 30x20) | P-11 | M28: =IF(OR(E28="",F28="",G28=""),"",E28*F28*G28/1000000000*IF(H28="",1,H28)) | N28: =IF(OR(E28="",F28=""),"",E28*F28/1000000*IF(H28="",1,H28)) | O28: =IF(E28="","",IF(K28<>"",K28,IF(AND(E28*F28*G28/1000000000<LISTS!$F$4,MAX(E28,F28,G28)<LISTS!$F$5),"D",IF(I28="N","C",IF(J28="Y","A-CURVED",IF(AND(MEDIAN(E28,F28,G28)<=LISTS!$F$10,MAX(E28,F28,G28)<=LISTS!$F$11),"B",IF(MAX(E28,F28,G28)>=LISTS!$F$3,"A","B"))))))) | R28: =IF(E28="","",IF(B28="","material?",IF(OR(F28="",G28=""),"size?",IF(I28="","exposed Y/N?",IF(H28="","qty?",IF(B28="OTHER","OTHER: no rate, price it under hardware","OK")))))) | S28: {=IF(OR(O28="",M28=""),"",IF(B28="MERANTI",RATES!$C$45,IFERROR(INDEX(RATES!$C:$C,MATCH(B28&"_"&SUBSTITUTE(O28,"-CURVED","C"),RATES!$A:$A,0)),"rate?")))} | T28: =IF(ISNUMBER(S28),M28*S28,"")
A29: 12 | M29: =IF(OR(E29="",F29="",G29=""),"",E29*F29*G29/1000000000*IF(H29="",1,H29)) | N29: =IF(OR(E29="",F29=""),"",E29*F29/1000000*IF(H29="",1,H29)) | O29: =IF(E29="","",IF(K29<>"",K29,IF(AND(E29*F29*G29/1000000000<LISTS!$F$4,MAX(E29,F29,G29)<LISTS!$F$5),"D",IF(I29="N","C",IF(J29="Y","A-CURVED",IF(AND(MEDIAN(E29,F29,G29)<=LISTS!$F$10,MAX(E29,F29,G29)<=LISTS!$F$11),"B",IF(MAX(E29,F29,G29)>=LISTS!$F$3,"A","B"))))))) | R29: =IF(E29="","",IF(B29="","material?",IF(OR(F29="",G29=""),"size?",IF(I29="","exposed Y/N?",IF(H29="","qty?",IF(B29="OTHER","OTHER: no rate, price it under hardware","OK")))))) | S29: {=IF(OR(O29="",M29=""),"",IF(B29="MERANTI",RATES!$C$45,IFERROR(INDEX(RATES!$C:$C,MATCH(B29&"_"&SUBSTITUTE(O29,"-CURVED","C"),RATES!$A:$A,0)),"rate?")))} | T29: =IF(ISNUMBER(S29),M29*S29,"")
A30: 13 | M30: =IF(OR(E30="",F30="",G30=""),"",E30*F30*G30/1000000000*IF(H30="",1,H30)) | N30: =IF(OR(E30="",F30=""),"",E30*F30/1000000*IF(H30="",1,H30)) | O30: =IF(E30="","",IF(K30<>"",K30,IF(AND(E30*F30*G30/1000000000<LISTS!$F$4,MAX(E30,F30,G30)<LISTS!$F$5),"D",IF(I30="N","C",IF(J30="Y","A-CURVED",IF(AND(MEDIAN(E30,F30,G30)<=LISTS!$F$10,MAX(E30,F30,G30)<=LISTS!$F$11),"B",IF(MAX(E30,F30,G30)>=LISTS!$F$3,"A","B"))))))) | R30: =IF(E30="","",IF(B30="","material?",IF(OR(F30="",G30=""),"size?",IF(I30="","exposed Y/N?",IF(H30="","qty?",IF(B30="OTHER","OTHER: no rate, price it under hardware","OK")))))) | S30: {=IF(OR(O30="",M30=""),"",IF(B30="MERANTI",RATES!$C$45,IFERROR(INDEX(RATES!$C:$C,MATCH(B30&"_"&SUBSTITUTE(O30,"-CURVED","C"),RATES!$A:$A,0)),"rate?")))} | T30: =IF(ISNUMBER(S30),M30*S30,"")
A31: 14 | M31: =IF(OR(E31="",F31="",G31=""),"",E31*F31*G31/1000000000*IF(H31="",1,H31)) | N31: =IF(OR(E31="",F31=""),"",E31*F31/1000000*IF(H31="",1,H31)) | O31: =IF(E31="","",IF(K31<>"",K31,IF(AND(E31*F31*G31/1000000000<LISTS!$F$4,MAX(E31,F31,G31)<LISTS!$F$5),"D",IF(I31="N","C",IF(J31="Y","A-CURVED",IF(AND(MEDIAN(E31,F31,G31)<=LISTS!$F$10,MAX(E31,F31,G31)<=LISTS!$F$11),"B",IF(MAX(E31,F31,G31)>=LISTS!$F$3,"A","B"))))))) | R31: =IF(E31="","",IF(B31="","material?",IF(OR(F31="",G31=""),"size?",IF(I31="","exposed Y/N?",IF(H31="","qty?",IF(B31="OTHER","OTHER: no rate, price it under hardware","OK")))))) | S31: {=IF(OR(O31="",M31=""),"",IF(B31="MERANTI",RATES!$C$45,IFERROR(INDEX(RATES!$C:$C,MATCH(B31&"_"&SUBSTITUTE(O31,"-CURVED","C"),RATES!$A:$A,0)),"rate?")))} | T31: =IF(ISNUMBER(S31),M31*S31,"")
A32: 15 | M32: =IF(OR(E32="",F32="",G32=""),"",E32*F32*G32/1000000000*IF(H32="",1,H32)) | N32: =IF(OR(E32="",F32=""),"",E32*F32/1000000*IF(H32="",1,H32)) | O32: =IF(E32="","",IF(K32<>"",K32,IF(AND(E32*F32*G32/1000000000<LISTS!$F$4,MAX(E32,F32,G32)<LISTS!$F$5),"D",IF(I32="N","C",IF(J32="Y","A-CURVED",IF(AND(MEDIAN(E32,F32,G32)<=LISTS!$F$10,MAX(E32,F32,G32)<=LISTS!$F$11),"B",IF(MAX(E32,F32,G32)>=LISTS!$F$3,"A","B"))))))) | R32: =IF(E32="","",IF(B32="","material?",IF(OR(F32="",G32=""),"size?",IF(I32="","exposed Y/N?",IF(H32="","qty?",IF(B32="OTHER","OTHER: no rate, price it under hardware","OK")))))) | S32: {=IF(OR(O32="",M32=""),"",IF(B32="MERANTI",RATES!$C$45,IFERROR(INDEX(RATES!$C:$C,MATCH(B32&"_"&SUBSTITUTE(O32,"-CURVED","C"),RATES!$A:$A,0)),"rate?")))} | T32: =IF(ISNUMBER(S32),M32*S32,"")
A33: 16 | M33: =IF(OR(E33="",F33="",G33=""),"",E33*F33*G33/1000000000*IF(H33="",1,H33)) | N33: =IF(OR(E33="",F33=""),"",E33*F33/1000000*IF(H33="",1,H33)) | O33: =IF(E33="","",IF(K33<>"",K33,IF(AND(E33*F33*G33/1000000000<LISTS!$F$4,MAX(E33,F33,G33)<LISTS!$F$5),"D",IF(I33="N","C",IF(J33="Y","A-CURVED",IF(AND(MEDIAN(E33,F33,G33)<=LISTS!$F$10,MAX(E33,F33,G33)<=LISTS!$F$11),"B",IF(MAX(E33,F33,G33)>=LISTS!$F$3,"A","B"))))))) | R33: =IF(E33="","",IF(B33="","material?",IF(OR(F33="",G33=""),"size?",IF(I33="","exposed Y/N?",IF(H33="","qty?",IF(B33="OTHER","OTHER: no rate, price it under hardware","OK")))))) | S33: {=IF(OR(O33="",M33=""),"",IF(B33="MERANTI",RATES!$C$45,IFERROR(INDEX(RATES!$C:$C,MATCH(B33&"_"&SUBSTITUTE(O33,"-CURVED","C"),RATES!$A:$A,0)),"rate?")))} | T33: =IF(ISNUMBER(S33),M33*S33,"")
A34: 17 | M34: =IF(OR(E34="",F34="",G34=""),"",E34*F34*G34/1000000000*IF(H34="",1,H34)) | N34: =IF(OR(E34="",F34=""),"",E34*F34/1000000*IF(H34="",1,H34)) | O34: =IF(E34="","",IF(K34<>"",K34,IF(AND(E34*F34*G34/1000000000<LISTS!$F$4,MAX(E34,F34,G34)<LISTS!$F$5),"D",IF(I34="N","C",IF(J34="Y","A-CURVED",IF(AND(MEDIAN(E34,F34,G34)<=LISTS!$F$10,MAX(E34,F34,G34)<=LISTS!$F$11),"B",IF(MAX(E34,F34,G34)>=LISTS!$F$3,"A","B"))))))) | R34: =IF(E34="","",IF(B34="","material?",IF(OR(F34="",G34=""),"size?",IF(I34="","exposed Y/N?",IF(H34="","qty?",IF(B34="OTHER","OTHER: no rate, price it under hardware","OK")))))) | S34: {=IF(OR(O34="",M34=""),"",IF(B34="MERANTI",RATES!$C$45,IFERROR(INDEX(RATES!$C:$C,MATCH(B34&"_"&SUBSTITUTE(O34,"-CURVED","C"),RATES!$A:$A,0)),"rate?")))} | T34: =IF(ISNUMBER(S34),M34*S34,"")
A35: 18 | M35: =IF(OR(E35="",F35="",G35=""),"",E35*F35*G35/1000000000*IF(H35="",1,H35)) | N35: =IF(OR(E35="",F35=""),"",E35*F35/1000000*IF(H35="",1,H35)) | O35: =IF(E35="","",IF(K35<>"",K35,IF(AND(E35*F35*G35/1000000000<LISTS!$F$4,MAX(E35,F35,G35)<LISTS!$F$5),"D",IF(I35="N","C",IF(J35="Y","A-CURVED",IF(AND(MEDIAN(E35,F35,G35)<=LISTS!$F$10,MAX(E35,F35,G35)<=LISTS!$F$11),"B",IF(MAX(E35,F35,G35)>=LISTS!$F$3,"A","B"))))))) | R35: =IF(E35="","",IF(B35="","material?",IF(OR(F35="",G35=""),"size?",IF(I35="","exposed Y/N?",IF(H35="","qty?",IF(B35="OTHER","OTHER: no rate, price it under hardware","OK")))))) | S35: {=IF(OR(O35="",M35=""),"",IF(B35="MERANTI",RATES!$C$45,IFERROR(INDEX(RATES!$C:$C,MATCH(B35&"_"&SUBSTITUTE(O35,"-CURVED","C"),RATES!$A:$A,0)),"rate?")))} | T35: =IF(ISNUMBER(S35),M35*S35,"")
A36: 19 | M36: =IF(OR(E36="",F36="",G36=""),"",E36*F36*G36/1000000000*IF(H36="",1,H36)) | N36: =IF(OR(E36="",F36=""),"",E36*F36/1000000*IF(H36="",1,H36)) | O36: =IF(E36="","",IF(K36<>"",K36,IF(AND(E36*F36*G36/1000000000<LISTS!$F$4,MAX(E36,F36,G36)<LISTS!$F$5),"D",IF(I36="N","C",IF(J36="Y","A-CURVED",IF(AND(MEDIAN(E36,F36,G36)<=LISTS!$F$10,MAX(E36,F36,G36)<=LISTS!$F$11),"B",IF(MAX(E36,F36,G36)>=LISTS!$F$3,"A","B"))))))) | R36: =IF(E36="","",IF(B36="","material?",IF(OR(F36="",G36=""),"size?",IF(I36="","exposed Y/N?",IF(H36="","qty?",IF(B36="OTHER","OTHER: no rate, price it under hardware","OK")))))) | S36: {=IF(OR(O36="",M36=""),"",IF(B36="MERANTI",RATES!$C$45,IFERROR(INDEX(RATES!$C:$C,MATCH(B36&"_"&SUBSTITUTE(O36,"-CURVED","C"),RATES!$A:$A,0)),"rate?")))} | T36: =IF(ISNUMBER(S36),M36*S36,"")
A37: 20 | M37: =IF(OR(E37="",F37="",G37=""),"",E37*F37*G37/1000000000*IF(H37="",1,H37)) | N37: =IF(OR(E37="",F37=""),"",E37*F37/1000000*IF(H37="",1,H37)) | O37: =IF(E37="","",IF(K37<>"",K37,IF(AND(E37*F37*G37/1000000000<LISTS!$F$4,MAX(E37,F37,G37)<LISTS!$F$5),"D",IF(I37="N","C",IF(J37="Y","A-CURVED",IF(AND(MEDIAN(E37,F37,G37)<=LISTS!$F$10,MAX(E37,F37,G37)<=LISTS!$F$11),"B",IF(MAX(E37,F37,G37)>=LISTS!$F$3,"A","B"))))))) | R37: =IF(E37="","",IF(B37="","material?",IF(OR(F37="",G37=""),"size?",IF(I37="","exposed Y/N?",IF(H37="","qty?",IF(B37="OTHER","OTHER: no rate, price it under hardware","OK")))))) | S37: {=IF(OR(O37="",M37=""),"",IF(B37="MERANTI",RATES!$C$45,IFERROR(INDEX(RATES!$C:$C,MATCH(B37&"_"&SUBSTITUTE(O37,"-CURVED","C"),RATES!$A:$A,0)),"rate?")))} | T37: =IF(ISNUMBER(S37),M37*S37,"")
A38: 21 | M38: =IF(OR(E38="",F38="",G38=""),"",E38*F38*G38/1000000000*IF(H38="",1,H38)) | N38: =IF(OR(E38="",F38=""),"",E38*F38/1000000*IF(H38="",1,H38)) | O38: =IF(E38="","",IF(K38<>"",K38,IF(AND(E38*F38*G38/1000000000<LISTS!$F$4,MAX(E38,F38,G38)<LISTS!$F$5),"D",IF(I38="N","C",IF(J38="Y","A-CURVED",IF(AND(MEDIAN(E38,F38,G38)<=LISTS!$F$10,MAX(E38,F38,G38)<=LISTS!$F$11),"B",IF(MAX(E38,F38,G38)>=LISTS!$F$3,"A","B"))))))) | R38: =IF(E38="","",IF(B38="","material?",IF(OR(F38="",G38=""),"size?",IF(I38="","exposed Y/N?",IF(H38="","qty?",IF(B38="OTHER","OTHER: no rate, price it under hardware","OK")))))) | S38: {=IF(OR(O38="",M38=""),"",IF(B38="MERANTI",RATES!$C$45,IFERROR(INDEX(RATES!$C:$C,MATCH(B38&"_"&SUBSTITUTE(O38,"-CURVED","C"),RATES!$A:$A,0)),"rate?")))} | T38: =IF(ISNUMBER(S38),M38*S38,"")
A39: 22 | M39: =IF(OR(E39="",F39="",G39=""),"",E39*F39*G39/1000000000*IF(H39="",1,H39)) | N39: =IF(OR(E39="",F39=""),"",E39*F39/1000000*IF(H39="",1,H39)) | O39: =IF(E39="","",IF(K39<>"",K39,IF(AND(E39*F39*G39/1000000000<LISTS!$F$4,MAX(E39,F39,G39)<LISTS!$F$5),"D",IF(I39="N","C",IF(J39="Y","A-CURVED",IF(AND(MEDIAN(E39,F39,G39)<=LISTS!$F$10,MAX(E39,F39,G39)<=LISTS!$F$11),"B",IF(MAX(E39,F39,G39)>=LISTS!$F$3,"A","B"))))))) | R39: =IF(E39="","",IF(B39="","material?",IF(OR(F39="",G39=""),"size?",IF(I39="","exposed Y/N?",IF(H39="","qty?",IF(B39="OTHER","OTHER: no rate, price it under hardware","OK")))))) | S39: {=IF(OR(O39="",M39=""),"",IF(B39="MERANTI",RATES!$C$45,IFERROR(INDEX(RATES!$C:$C,MATCH(B39&"_"&SUBSTITUTE(O39,"-CURVED","C"),RATES!$A:$A,0)),"rate?")))} | T39: =IF(ISNUMBER(S39),M39*S39,"")
A40: 23 | M40: =IF(OR(E40="",F40="",G40=""),"",E40*F40*G40/1000000000*IF(H40="",1,H40)) | N40: =IF(OR(E40="",F40=""),"",E40*F40/1000000*IF(H40="",1,H40)) | O40: =IF(E40="","",IF(K40<>"",K40,IF(AND(E40*F40*G40/1000000000<LISTS!$F$4,MAX(E40,F40,G40)<LISTS!$F$5),"D",IF(I40="N","C",IF(J40="Y","A-CURVED",IF(AND(MEDIAN(E40,F40,G40)<=LISTS!$F$10,MAX(E40,F40,G40)<=LISTS!$F$11),"B",IF(MAX(E40,F40,G40)>=LISTS!$F$3,"A","B"))))))) | R40: =IF(E40="","",IF(B40="","material?",IF(OR(F40="",G40=""),"size?",IF(I40="","exposed Y/N?",IF(H40="","qty?",IF(B40="OTHER","OTHER: no rate, price it under hardware","OK")))))) | S40: {=IF(OR(O40="",M40=""),"",IF(B40="MERANTI",RATES!$C$45,IFERROR(INDEX(RATES!$C:$C,MATCH(B40&"_"&SUBSTITUTE(O40,"-CURVED","C"),RATES!$A:$A,0)),"rate?")))} | T40: =IF(ISNUMBER(S40),M40*S40,"")
... A42: 25 | M42: =IF(OR(E42="",F42="",G42=""),"",E42*F42*G42/1000000000*IF(H42="",1,H42)) | N42: =IF(OR(E42="",F42=""),"",E42*F42/1000000*IF(H42="",1,H42)) | O42: =IF(E42="","",IF(K42<>"",K42,IF(AND(E42*F42*G42/1000000000<LISTS!$F$4,MAX(E42,F42,G42)<LISTS!$F$5),"D",IF(I42="N","C",IF(J42="Y","A-CURVED",IF(AND(MEDIAN(E42,F42,G42)<=LISTS!$F$10,MAX(E42,F42,G42)<=LISTS!$F$11),"B",IF(MAX(E42,F42,G42)>=LISTS!$F$3,"A","B"))))))) | R42: =IF(E42="","",IF(B42="","material?",IF(OR(F42="",G42=""),"size?",IF(I42="","exposed Y/N?",IF(H42="","qty?",IF(B42="OTHER","OTHER: no rate, price it under hardware","OK")))))) | S42: {=IF(OR(O42="",M42=""),"",IF(B42="MERANTI",RATES!$C$45,IFERROR(INDEX(RATES!$C:$C,MATCH(B42&"_"&SUBSTITUTE(O42,"-CURVED","C"),RATES!$A:$A,0)),"rate?")))} | T42: =IF(ISNUMBER(S42),M42*S42,"")
A44: PANELS: one line per panel, L × W in mm, T = board thickness, qty per item. No size (round, oversize, laminated): enter SHEETS (manual)
A45: NO | B45: PANEL TYPE | C45: LABEL | D45: COMPONENT | E45: L mm | F45: W mm | G45: T mm | H45: QTY | I45: EXPOSED FACES (0/1/2) | K45: SHEETS (manual) | L45: NOTE | M45: VOL m³ (calc) | N45: FACE m² (calc) | O45: PIECES/SHEET (calc) | P45: SHEETS (calc) | Q45: WASTE % (calc) | R45: CHECK (calc) | S45: RATE (system) | T45: COST IDR (system)
A46: 1 | B46: PLY-18-MSF | C46: 20 / B-18-1X | D46: Top Cap Panel (Veneer Mindi 1F) | E46: 1500 | F46: 450 | G46: 18 | H46: 1 | I46: 1 | L46: Part 20 / Code B-18-1X | Plywood 18mm MSF | M46: =IF(OR(E46="",F46="",G46=""),"",E46*F46*G46/1000000000*IF(H46="",1,H46)) | N46: =IF(OR(E46="",F46=""),"",E46*F46/1000000*IF(H46="",1,H46)) | O46: =IF(OR(E46="",F46=""),"",MAX(INT(LISTS!$F$6/(E46+LISTS!$F$8))*INT(LISTS!$F$7/(F46+LISTS!$F$8)),INT(LISTS!$F$6/(F46+LISTS!$F$8))*INT(LISTS!$F$7/(E46+LISTS!$F$8)))) | P46: =IF(K46<>"",K46,IF(OR(O46="",O46=0),"",IF(H46="",1,H46)/O46)) | Q46: =IF(OR(K46<>"",P46=""),"",1-(IF(H46="",1,H46)*E46*F46)/(ROUNDUP(P46,0)*LISTS!$F$6*LISTS!$F$7)) | R46: =IF(AND(E46="",K46=""),"",IF(B46="","panel type?",IF(AND(K46="",O46=0),"panel bigger than sheet",IF(AND(G46<>"",IFERROR(VALUE(MID(B46,5,FIND("-",B46,5)-5)),0)<>G46),"T must match panel type",IF(I46="","exposed faces?","OK"))))) | S46: {=IF(OR(B46="",P46=""),"",IFERROR(INDEX(RATES!$C:$C,MATCH(B46,RATES!$A:$A,0)),"rate?"))} | T46: =IF(ISNUMBER(S46),IF(K46<>"",K46,IF(Q46>RATES!$C$97,P46*(1+RATES!$C$98),ROUNDUP(P46,0)))*S46,"")
A47: 2 | B47: PLY-9-MSF | C47: 13 / B-9-1X | D47: Dinding Samping (Left & Right) | E47: 600 | F47: 360 | G47: 9 | H47: 2 | I47: 1 | L47: Part 13 / Code B-9-1X | Plywood 9mm MSF | M47: =IF(OR(E47="",F47="",G47=""),"",E47*F47*G47/1000000000*IF(H47="",1,H47)) | N47: =IF(OR(E47="",F47=""),"",E47*F47/1000000*IF(H47="",1,H47)) | O47: =IF(OR(E47="",F47=""),"",MAX(INT(LISTS!$F$6/(E47+LISTS!$F$8))*INT(LISTS!$F$7/(F47+LISTS!$F$8)),INT(LISTS!$F$6/(F47+LISTS!$F$8))*INT(LISTS!$F$7/(E47+LISTS!$F$8)))) | P47: =IF(K47<>"",K47,IF(OR(O47="",O47=0),"",IF(H47="",1,H47)/O47)) | Q47: =IF(OR(K47<>"",P47=""),"",1-(IF(H47="",1,H47)*E47*F47)/(ROUNDUP(P47,0)*LISTS!$F$6*LISTS!$F$7)) | R47: =IF(AND(E47="",K47=""),"",IF(B47="","panel type?",IF(AND(K47="",O47=0),"panel bigger than sheet",IF(AND(G47<>"",IFERROR(VALUE(MID(B47,5,FIND("-",B47,5)-5)),0)<>G47),"T must match panel type",IF(I47="","exposed faces?","OK"))))) | S47: {=IF(OR(B47="",P47=""),"",IFERROR(INDEX(RATES!$C:$C,MATCH(B47,RATES!$A:$A,0)),"rate?"))} | T47: =IF(ISNUMBER(S47),IF(K47<>"",K47,IF(Q47>RATES!$C$97,P47*(1+RATES!$C$98),ROUNDUP(P47,0)))*S47,"")
A48: 3 | B48: PLY-9-RAW | C48: 5 / B-9-0X | D48: Dinding Pembagi Tengah | E48: 600 | F48: 360 | G48: 9 | H48: 1 | I48: 0 | L48: Part 5 / Code B-9-0X | Plywood 9mm RAW | M48: =IF(OR(E48="",F48="",G48=""),"",E48*F48*G48/1000000000*IF(H48="",1,H48)) | N48: =IF(OR(E48="",F48=""),"",E48*F48/1000000*IF(H48="",1,H48)) | O48: =IF(OR(E48="",F48=""),"",MAX(INT(LISTS!$F$6/(E48+LISTS!$F$8))*INT(LISTS!$F$7/(F48+LISTS!$F$8)),INT(LISTS!$F$6/(F48+LISTS!$F$8))*INT(LISTS!$F$7/(E48+LISTS!$F$8)))) | P48: =IF(K48<>"",K48,IF(OR(O48="",O48=0),"",IF(H48="",1,H48)/O48)) | Q48: =IF(OR(K48<>"",P48=""),"",1-(IF(H48="",1,H48)*E48*F48)/(ROUNDUP(P48,0)*LISTS!$F$6*LISTS!$F$7)) | R48: =IF(AND(E48="",K48=""),"",IF(B48="","panel type?",IF(AND(K48="",O48=0),"panel bigger than sheet",IF(AND(G48<>"",IFERROR(VALUE(MID(B48,5,FIND("-",B48,5)-5)),0)<>G48),"T must match panel type",IF(I48="","exposed faces?","OK"))))) | S48: {=IF(OR(B48="",P48=""),"",IFERROR(INDEX(RATES!$C:$C,MATCH(B48,RATES!$A:$A,0)),"rate?"))} | T48: =IF(ISNUMBER(S48),IF(K48<>"",K48,IF(Q48>RATES!$C$97,P48*(1+RATES!$C$98),ROUNDUP(P48,0)))*S48,"")
A49: 4 | B49: PLY-9-RAW | C49: 12 / B-9-0X | D49: Dinding Belakang (Backing Panel) | E49: 1410 | F49: 600 | G49: 9 | H49: 1 | I49: 0 | L49: Part 12 / Code B-9-0X | Plywood 9mm RAW | M49: =IF(OR(E49="",F49="",G49=""),"",E49*F49*G49/1000000000*IF(H49="",1,H49)) | N49: =IF(OR(E49="",F49=""),"",E49*F49/1000000*IF(H49="",1,H49)) | O49: =IF(OR(E49="",F49=""),"",MAX(INT(LISTS!$F$6/(E49+LISTS!$F$8))*INT(LISTS!$F$7/(F49+LISTS!$F$8)),INT(LISTS!$F$6/(F49+LISTS!$F$8))*INT(LISTS!$F$7/(E49+LISTS!$F$8)))) | P49: =IF(K49<>"",K49,IF(OR(O49="",O49=0),"",IF(H49="",1,H49)/O49)) | Q49: =IF(OR(K49<>"",P49=""),"",1-(IF(H49="",1,H49)*E49*F49)/(ROUNDUP(P49,0)*LISTS!$F$6*LISTS!$F$7)) | R49: =IF(AND(E49="",K49=""),"",IF(B49="","panel type?",IF(AND(K49="",O49=0),"panel bigger than sheet",IF(AND(G49<>"",IFERROR(VALUE(MID(B49,5,FIND("-",B49,5)-5)),0)<>G49),"T must match panel type",IF(I49="","exposed faces?","OK"))))) | S49: {=IF(OR(B49="",P49=""),"",IFERROR(INDEX(RATES!$C:$C,MATCH(B49,RATES!$A:$A,0)),"rate?"))} | T49: =IF(ISNUMBER(S49),IF(K49<>"",K49,IF(Q49>RATES!$C$97,P49*(1+RATES!$C$98),ROUNDUP(P49,0)))*S49,"")
A50: 5 | B50: PLY-12-RAW | C50: 8 / B-12-0X | D50: Kotak Laci Dinding Samping | E50: 350 | F50: 140 | G50: 12 | H50: 12 | I50: 0 | L50: Part 8 / Code B-12-0X | Plywood 12mm RAW | M50: =IF(OR(E50="",F50="",G50=""),"",E50*F50*G50/1000000000*IF(H50="",1,H50)) | N50: =IF(OR(E50="",F50=""),"",E50*F50/1000000*IF(H50="",1,H50)) | O50: =IF(OR(E50="",F50=""),"",MAX(INT(LISTS!$F$6/(E50+LISTS!$F$8))*INT(LISTS!$F$7/(F50+LISTS!$F$8)),INT(LISTS!$F$6/(F50+LISTS!$F$8))*INT(LISTS!$F$7/(E50+LISTS!$F$8)))) | P50: =IF(K50<>"",K50,IF(OR(O50="",O50=0),"",IF(H50="",1,H50)/O50)) | Q50: =IF(OR(K50<>"",P50=""),"",1-(IF(H50="",1,H50)*E50*F50)/(ROUNDUP(P50,0)*LISTS!$F$6*LISTS!$F$7)) | R50: =IF(AND(E50="",K50=""),"",IF(B50="","panel type?",IF(AND(K50="",O50=0),"panel bigger than sheet",IF(AND(G50<>"",IFERROR(VALUE(MID(B50,5,FIND("-",B50,5)-5)),0)<>G50),"T must match panel type",IF(I50="","exposed faces?","OK"))))) | S50: {=IF(OR(B50="",P50=""),"",IFERROR(INDEX(RATES!$C:$C,MATCH(B50,RATES!$A:$A,0)),"rate?"))} | T50: =IF(ISNUMBER(S50),IF(K50<>"",K50,IF(Q50>RATES!$C$97,P50*(1+RATES!$C$98),ROUNDUP(P50,0)))*S50,"")
A51: 6 | B51: PLY-12-RAW | C51: 9 / B-12-0X | D51: Kotak Laci Muka & Belakang | E51: 621 | F51: 140 | G51: 12 | H51: 12 | I51: 0 | L51: Part 9 / Code B-12-0X | Plywood 12mm RAW | M51: =IF(OR(E51="",F51="",G51=""),"",E51*F51*G51/1000000000*IF(H51="",1,H51)) | N51: =IF(OR(E51="",F51=""),"",E51*F51/1000000*IF(H51="",1,H51)) | O51: =IF(OR(E51="",F51=""),"",MAX(INT(LISTS!$F$6/(E51+LISTS!$F$8))*INT(LISTS!$F$7/(F51+LISTS!$F$8)),INT(LISTS!$F$6/(F51+LISTS!$F$8))*INT(LISTS!$F$7/(E51+LISTS!$F$8)))) | P51: =IF(K51<>"",K51,IF(OR(O51="",O51=0),"",IF(H51="",1,H51)/O51)) | Q51: =IF(OR(K51<>"",P51=""),"",1-(IF(H51="",1,H51)*E51*F51)/(ROUNDUP(P51,0)*LISTS!$F$6*LISTS!$F$7)) | R51: =IF(AND(E51="",K51=""),"",IF(B51="","panel type?",IF(AND(K51="",O51=0),"panel bigger than sheet",IF(AND(G51<>"",IFERROR(VALUE(MID(B51,5,FIND("-",B51,5)-5)),0)<>G51),"T must match panel type",IF(I51="","exposed faces?","OK"))))) | S51: {=IF(OR(B51="",P51=""),"",IFERROR(INDEX(RATES!$C:$C,MATCH(B51,RATES!$A:$A,0)),"rate?"))} | T51: =IF(ISNUMBER(S51),IF(K51<>"",K51,IF(Q51>RATES!$C$97,P51*(1+RATES!$C$98),ROUNDUP(P51,0)))*S51,"")
A52: 7 | B52: PLY-6-RAW | C52: 10 / B-6-0X | D52: Alas Dasar Laci (Drawer Bottom) | E52: 633 | F52: 338 | G52: 6 | H52: 6 | I52: 0 | L52: Part 10 / Code B-6-0X | Plywood 6mm RAW | M52: =IF(OR(E52="",F52="",G52=""),"",E52*F52*G52/1000000000*IF(H52="",1,H52)) | N52: =IF(OR(E52="",F52=""),"",E52*F52/1000000*IF(H52="",1,H52)) | O52: =IF(OR(E52="",F52=""),"",MAX(INT(LISTS!$F$6/(E52+LISTS!$F$8))*INT(LISTS!$F$7/(F52+LISTS!$F$8)),INT(LISTS!$F$6/(F52+LISTS!$F$8))*INT(LISTS!$F$7/(E52+LISTS!$F$8)))) | P52: =IF(K52<>"",K52,IF(OR(O52="",O52=0),"",IF(H52="",1,H52)/O52)) | Q52: =IF(OR(K52<>"",P52=""),"",1-(IF(H52="",1,H52)*E52*F52)/(ROUNDUP(P52,0)*LISTS!$F$6*LISTS!$F$7)) | R52: =IF(AND(E52="",K52=""),"",IF(B52="","panel type?",IF(AND(K52="",O52=0),"panel bigger than sheet",IF(AND(G52<>"",IFERROR(VALUE(MID(B52,5,FIND("-",B52,5)-5)),0)<>G52),"T must match panel type",IF(I52="","exposed faces?","OK"))))) | S52: {=IF(OR(B52="",P52=""),"",IFERROR(INDEX(RATES!$C:$C,MATCH(B52,RATES!$A:$A,0)),"rate?"))} | T52: =IF(ISNUMBER(S52),IF(K52<>"",K52,IF(Q52>RATES!$C$97,P52*(1+RATES!$C$98),ROUNDUP(P52,0)))*S52,"")
A53: 8 | M53: =IF(OR(E53="",F53="",G53=""),"",E53*F53*G53/1000000000*IF(H53="",1,H53)) | N53: =IF(OR(E53="",F53=""),"",E53*F53/1000000*IF(H53="",1,H53)) | O53: =IF(OR(E53="",F53=""),"",MAX(INT(LISTS!$F$6/(E53+LISTS!$F$8))*INT(LISTS!$F$7/(F53+LISTS!$F$8)),INT(LISTS!$F$6/(F53+LISTS!$F$8))*INT(LISTS!$F$7/(E53+LISTS!$F$8)))) | P53: =IF(K53<>"",K53,IF(OR(O53="",O53=0),"",IF(H53="",1,H53)/O53)) | Q53: =IF(OR(K53<>"",P53=""),"",1-(IF(H53="",1,H53)*E53*F53)/(ROUNDUP(P53,0)*LISTS!$F$6*LISTS!$F$7)) | R53: =IF(AND(E53="",K53=""),"",IF(B53="","panel type?",IF(AND(K53="",O53=0),"panel bigger than sheet",IF(AND(G53<>"",IFERROR(VALUE(MID(B53,5,FIND("-",B53,5)-5)),0)<>G53),"T must match panel type",IF(I53="","exposed faces?","OK"))))) | S53: {=IF(OR(B53="",P53=""),"",IFERROR(INDEX(RATES!$C:$C,MATCH(B53,RATES!$A:$A,0)),"rate?"))} | T53: =IF(ISNUMBER(S53),IF(K53<>"",K53,IF(Q53>RATES!$C$97,P53*(1+RATES!$C$98),ROUNDUP(P53,0)))*S53,"")
A54: 9 | M54: =IF(OR(E54="",F54="",G54=""),"",E54*F54*G54/1000000000*IF(H54="",1,H54)) | N54: =IF(OR(E54="",F54=""),"",E54*F54/1000000*IF(H54="",1,H54)) | O54: =IF(OR(E54="",F54=""),"",MAX(INT(LISTS!$F$6/(E54+LISTS!$F$8))*INT(LISTS!$F$7/(F54+LISTS!$F$8)),INT(LISTS!$F$6/(F54+LISTS!$F$8))*INT(LISTS!$F$7/(E54+LISTS!$F$8)))) | P54: =IF(K54<>"",K54,IF(OR(O54="",O54=0),"",IF(H54="",1,H54)/O54)) | Q54: =IF(OR(K54<>"",P54=""),"",1-(IF(H54="",1,H54)*E54*F54)/(ROUNDUP(P54,0)*LISTS!$F$6*LISTS!$F$7)) | R54: =IF(AND(E54="",K54=""),"",IF(B54="","panel type?",IF(AND(K54="",O54=0),"panel bigger than sheet",IF(AND(G54<>"",IFERROR(VALUE(MID(B54,5,FIND("-",B54,5)-5)),0)<>G54),"T must match panel type",IF(I54="","exposed faces?","OK"))))) | S54: {=IF(OR(B54="",P54=""),"",IFERROR(INDEX(RATES!$C:$C,MATCH(B54,RATES!$A:$A,0)),"rate?"))} | T54: =IF(ISNUMBER(S54),IF(K54<>"",K54,IF(Q54>RATES!$C$97,P54*(1+RATES!$C$98),ROUNDUP(P54,0)))*S54,"")
A55: 10 | M55: =IF(OR(E55="",F55="",G55=""),"",E55*F55*G55/1000000000*IF(H55="",1,H55)) | N55: =IF(OR(E55="",F55=""),"",E55*F55/1000000*IF(H55="",1,H55)) | O55: =IF(OR(E55="",F55=""),"",MAX(INT(LISTS!$F$6/(E55+LISTS!$F$8))*INT(LISTS!$F$7/(F55+LISTS!$F$8)),INT(LISTS!$F$6/(F55+LISTS!$F$8))*INT(LISTS!$F$7/(E55+LISTS!$F$8)))) | P55: =IF(K55<>"",K55,IF(OR(O55="",O55=0),"",IF(H55="",1,H55)/O55)) | Q55: =IF(OR(K55<>"",P55=""),"",1-(IF(H55="",1,H55)*E55*F55)/(ROUNDUP(P55,0)*LISTS!$F$6*LISTS!$F$7)) | R55: =IF(AND(E55="",K55=""),"",IF(B55="","panel type?",IF(AND(K55="",O55=0),"panel bigger than sheet",IF(AND(G55<>"",IFERROR(VALUE(MID(B55,5,FIND("-",B55,5)-5)),0)<>G55),"T must match panel type",IF(I55="","exposed faces?","OK"))))) | S55: {=IF(OR(B55="",P55=""),"",IFERROR(INDEX(RATES!$C:$C,MATCH(B55,RATES!$A:$A,0)),"rate?"))} | T55: =IF(ISNUMBER(S55),IF(K55<>"",K55,IF(Q55>RATES!$C$97,P55*(1+RATES!$C$98),ROUNDUP(P55,0)))*S55,"")
A56: 11 | M56: =IF(OR(E56="",F56="",G56=""),"",E56*F56*G56/1000000000*IF(H56="",1,H56)) | N56: =IF(OR(E56="",F56=""),"",E56*F56/1000000*IF(H56="",1,H56)) | O56: =IF(OR(E56="",F56=""),"",MAX(INT(LISTS!$F$6/(E56+LISTS!$F$8))*INT(LISTS!$F$7/(F56+LISTS!$F$8)),INT(LISTS!$F$6/(F56+LISTS!$F$8))*INT(LISTS!$F$7/(E56+LISTS!$F$8)))) | P56: =IF(K56<>"",K56,IF(OR(O56="",O56=0),"",IF(H56="",1,H56)/O56)) | Q56: =IF(OR(K56<>"",P56=""),"",1-(IF(H56="",1,H56)*E56*F56)/(ROUNDUP(P56,0)*LISTS!$F$6*LISTS!$F$7)) | R56: =IF(AND(E56="",K56=""),"",IF(B56="","panel type?",IF(AND(K56="",O56=0),"panel bigger than sheet",IF(AND(G56<>"",IFERROR(VALUE(MID(B56,5,FIND("-",B56,5)-5)),0)<>G56),"T must match panel type",IF(I56="","exposed faces?","OK"))))) | S56: {=IF(OR(B56="",P56=""),"",IFERROR(INDEX(RATES!$C:$C,MATCH(B56,RATES!$A:$A,0)),"rate?"))} | T56: =IF(ISNUMBER(S56),IF(K56<>"",K56,IF(Q56>RATES!$C$97,P56*(1+RATES!$C$98),ROUNDUP(P56,0)))*S56,"")
A57: 12 | M57: =IF(OR(E57="",F57="",G57=""),"",E57*F57*G57/1000000000*IF(H57="",1,H57)) | N57: =IF(OR(E57="",F57=""),"",E57*F57/1000000*IF(H57="",1,H57)) | O57: =IF(OR(E57="",F57=""),"",MAX(INT(LISTS!$F$6/(E57+LISTS!$F$8))*INT(LISTS!$F$7/(F57+LISTS!$F$8)),INT(LISTS!$F$6/(F57+LISTS!$F$8))*INT(LISTS!$F$7/(E57+LISTS!$F$8)))) | P57: =IF(K57<>"",K57,IF(OR(O57="",O57=0),"",IF(H57="",1,H57)/O57)) | Q57: =IF(OR(K57<>"",P57=""),"",1-(IF(H57="",1,H57)*E57*F57)/(ROUNDUP(P57,0)*LISTS!$F$6*LISTS!$F$7)) | R57: =IF(AND(E57="",K57=""),"",IF(B57="","panel type?",IF(AND(K57="",O57=0),"panel bigger than sheet",IF(AND(G57<>"",IFERROR(VALUE(MID(B57,5,FIND("-",B57,5)-5)),0)<>G57),"T must match panel type",IF(I57="","exposed faces?","OK"))))) | S57: {=IF(OR(B57="",P57=""),"",IFERROR(INDEX(RATES!$C:$C,MATCH(B57,RATES!$A:$A,0)),"rate?"))} | T57: =IF(ISNUMBER(S57),IF(K57<>"",K57,IF(Q57>RATES!$C$97,P57*(1+RATES!$C$98),ROUNDUP(P57,0)))*S57,"")
A58: 13 | M58: =IF(OR(E58="",F58="",G58=""),"",E58*F58*G58/1000000000*IF(H58="",1,H58)) | N58: =IF(OR(E58="",F58=""),"",E58*F58/1000000*IF(H58="",1,H58)) | O58: =IF(OR(E58="",F58=""),"",MAX(INT(LISTS!$F$6/(E58+LISTS!$F$8))*INT(LISTS!$F$7/(F58+LISTS!$F$8)),INT(LISTS!$F$6/(F58+LISTS!$F$8))*INT(LISTS!$F$7/(E58+LISTS!$F$8)))) | P58: =IF(K58<>"",K58,IF(OR(O58="",O58=0),"",IF(H58="",1,H58)/O58)) | Q58: =IF(OR(K58<>"",P58=""),"",1-(IF(H58="",1,H58)*E58*F58)/(ROUNDUP(P58,0)*LISTS!$F$6*LISTS!$F$7)) | R58: =IF(AND(E58="",K58=""),"",IF(B58="","panel type?",IF(AND(K58="",O58=0),"panel bigger than sheet",IF(AND(G58<>"",IFERROR(VALUE(MID(B58,5,FIND("-",B58,5)-5)),0)<>G58),"T must match panel type",IF(I58="","exposed faces?","OK"))))) | S58: {=IF(OR(B58="",P58=""),"",IFERROR(INDEX(RATES!$C:$C,MATCH(B58,RATES!$A:$A,0)),"rate?"))} | T58: =IF(ISNUMBER(S58),IF(K58<>"",K58,IF(Q58>RATES!$C$97,P58*(1+RATES!$C$98),ROUNDUP(P58,0)))*S58,"")
A59: 14 | M59: =IF(OR(E59="",F59="",G59=""),"",E59*F59*G59/1000000000*IF(H59="",1,H59)) | N59: =IF(OR(E59="",F59=""),"",E59*F59/1000000*IF(H59="",1,H59)) | O59: =IF(OR(E59="",F59=""),"",MAX(INT(LISTS!$F$6/(E59+LISTS!$F$8))*INT(LISTS!$F$7/(F59+LISTS!$F$8)),INT(LISTS!$F$6/(F59+LISTS!$F$8))*INT(LISTS!$F$7/(E59+LISTS!$F$8)))) | P59: =IF(K59<>"",K59,IF(OR(O59="",O59=0),"",IF(H59="",1,H59)/O59)) | Q59: =IF(OR(K59<>"",P59=""),"",1-(IF(H59="",1,H59)*E59*F59)/(ROUNDUP(P59,0)*LISTS!$F$6*LISTS!$F$7)) | R59: =IF(AND(E59="",K59=""),"",IF(B59="","panel type?",IF(AND(K59="",O59=0),"panel bigger than sheet",IF(AND(G59<>"",IFERROR(VALUE(MID(B59,5,FIND("-",B59,5)-5)),0)<>G59),"T must match panel type",IF(I59="","exposed faces?","OK"))))) | S59: {=IF(OR(B59="",P59=""),"",IFERROR(INDEX(RATES!$C:$C,MATCH(B59,RATES!$A:$A,0)),"rate?"))} | T59: =IF(ISNUMBER(S59),IF(K59<>"",K59,IF(Q59>RATES!$C$97,P59*(1+RATES!$C$98),ROUNDUP(P59,0)))*S59,"")
A60: 15 | M60: =IF(OR(E60="",F60="",G60=""),"",E60*F60*G60/1000000000*IF(H60="",1,H60)) | N60: =IF(OR(E60="",F60=""),"",E60*F60/1000000*IF(H60="",1,H60)) | O60: =IF(OR(E60="",F60=""),"",MAX(INT(LISTS!$F$6/(E60+LISTS!$F$8))*INT(LISTS!$F$7/(F60+LISTS!$F$8)),INT(LISTS!$F$6/(F60+LISTS!$F$8))*INT(LISTS!$F$7/(E60+LISTS!$F$8)))) | P60: =IF(K60<>"",K60,IF(OR(O60="",O60=0),"",IF(H60="",1,H60)/O60)) | Q60: =IF(OR(K60<>"",P60=""),"",1-(IF(H60="",1,H60)*E60*F60)/(ROUNDUP(P60,0)*LISTS!$F$6*LISTS!$F$7)) | R60: =IF(AND(E60="",K60=""),"",IF(B60="","panel type?",IF(AND(K60="",O60=0),"panel bigger than sheet",IF(AND(G60<>"",IFERROR(VALUE(MID(B60,5,FIND("-",B60,5)-5)),0)<>G60),"T must match panel type",IF(I60="","exposed faces?","OK"))))) | S60: {=IF(OR(B60="",P60=""),"",IFERROR(INDEX(RATES!$C:$C,MATCH(B60,RATES!$A:$A,0)),"rate?"))} | T60: =IF(ISNUMBER(S60),IF(K60<>"",K60,IF(Q60>RATES!$C$97,P60*(1+RATES!$C$98),ROUNDUP(P60,0)))*S60,"")
A62: HARDWARE & BOUGHT-IN: runners, hinges, handles, metal frames, rattan, glass, mirror, fabric, foam, outside labour. ENTER UNIT PRICE IDR.
A63: NO | B63: ITEM MASTER CODE | C63: LABEL | D63: DESCRIPTION | E63: VENDOR | H63: QTY | I63: UOM | L63: LINK / NOTE | S63: UNIT PRICE IDR | T63: LINE TOTAL (calc)
A64: 1 | B64: HARDWARE | C64: D2 / DTC-14 | D64: Rel laci DTC soft close 14" (356 mm) | E64: Sukey / DTC | H64: 6 | I64: set | L64: Part D2 / Code D2 | Rel laci DTC soft close 14" | S64: 61396.2 | T64: =IF(OR(H64="",S64=""),"",H64*S64)
A65: 2 | B65: BOUGHT-IN | C65: ROTAN / SQ | D65: Anyaman Rotan Kotak Alami (Square Cane Mesh) | E65: Lokal | H65: 1.5 | I65: m lari | L65: Inlay Muka Laci | Anyaman Rotan Kotak Alami | S65: 160000 | T65: =IF(OR(H65="",S65=""),"",H65*S65)
A66: 3 | B66: HARDWARE | C66: HNDL / 128MM | D66: Handle, solid brass / custom wood 128 mm | E66: Lokal | H66: 6 | I66: pcs | L66: Handle, solid brass / custom wood 128 mm | S66: 25000 | T66: =IF(OR(H66="",S66=""),"",H66*S66)
A67: 4 | B67: HARDWARE | C67: GLIDES / 25MM | D67: Nylon glides 25 mm | E67: Lokal | H67: 6 | I67: pcs | L67: Nylon glides 25 mm | S67: 3500 | T67: =IF(OR(H67="",S67=""),"",H67*S67)
A68: 5 | T68: =IF(OR(H68="",S68=""),"",H68*S68)
A69: 6 | T69: =IF(OR(H69="",S69=""),"",H69*S69)
A70: 7 | T70: =IF(OR(H70="",S70=""),"",H70*S70)
A71: 8 | T71: =IF(OR(H71="",S71=""),"",H71*S71)
A72: 9 | T72: =IF(OR(H72="",S72=""),"",H72*S72)
A73: 10 | T73: =IF(OR(H73="",S73=""),"",H73*S73)
A74: 11 | T74: =IF(OR(H74="",S74=""),"",H74*S74)
A75: 12 | T75: =IF(OR(H75="",S75=""),"",H75*S75)
A76: 13 | T76: =IF(OR(H76="",S76=""),"",H76*S76)
A77: 14 | T77: =IF(OR(H77="",S77=""),"",H77*S77)
A78: 15 | T78: =IF(OR(H78="",S78=""),"",H78*S78)
A81: SUMMARY (system): cost per ONE item, from the RATES tab. Do not type here. | E81: COST USD (system)
C82: Solid wood m³ | D82: =SUM(M18:M42)
C83: Panel sheets | D83: =SUM(P46:P60)
C84: Finishing m² (exposed) | D84: =SUMIF(I18:I42,"Y",N18:N42)+SUMIF(I46:I60,1,N46:N60)+2*SUMIF(I46:I60,2,N46:N60) | F84: one face (L × W) per exposed solid component + exposed panel faces
C85: Cartons | D85: =G15
C86: Carton m³ | D86: =M15
C87: TIMBER | D87: =SUM(T18:T42) | F87: Σ component m³ × tier rate (yield, processing and carpentry labour inside)
C88: FASTENERS | D88: =D82*RATES!$C$46 | F88: solid wood m³ × FASTENERS
C89: PANELS | D89: =SUM(T46:T60) | F89: sheets charged × sheet rate (nested, or manual sheets)
C90: FINISHING MATERIALS | D90: =D84*RATES!$C$47*IF($C$5="NONE (RAW)",0,1) | F90: exposed m² × FIN_MAT (Zhanchen + thinner). All four finishing lines = 0 when FINISH RECIPE is NONE (RAW)
C91: SANDING MATERIALS | D91: =D84*RATES!$C$48*IF($C$5="NONE (RAW)",0,1) | F91: exposed m² × SAND_MAT (abrasives)
C92: SANDING LABOUR | D92: =D84*RATES!$C$49*IF($C$5="NONE (RAW)",0,1) | F92: exposed m² × SAND_LAB
C93: FINISHING LABOUR | D93: =D84*RATES!$C$50*IF($C$5="NONE (RAW)",0,1) | F93: exposed m² × FIN_LAB
C94: HARDWARE | D94: =SUM(T64:T78) | F94: Σ hardware & bought-in lines (qty × unit price entered by the team)
C95: PACKING | D95: =IF(L15=0,0,IF(L15<RATES!$C$95,RATES!$C$53*G15,L15*RATES!$C$51*(1+IF(G15>1,RATES!$C$96,0)))+M15*RATES!$C$52) | F95: carton m² × CARTON_M2 + carton m³ × PACK_LAB
C96: TOTAL COST | D96: =SUM(D87:D95) | F96: Σ of the nine lines above
C97: MISC 4% | D97: =D96*RATES!$C$54 | F97: total cost × MISC_PCT
C98: DIRECT COST IDR (HPP) | D98: =D96+D97 | F98: total cost + misc
B99: =RATES!$C$169 | C99: DIRECT COST USD | D99: =D98/RATES!$C$169 | F99: HPP ÷ FX_TARGET (IDR/USD in column B)
C100: TARGET PRICE USD | D100: =D99*RATES!$C$55 | F100: direct cost USD × TARGET_X
C101: ORDER QTY × DIRECT COST IDR | D101: =IF(ISNUMBER(C4),C4,0)*D98
C102: Open input checks | D102: =COUNTIF(R18:R42,"?*")-COUNTIF(R18:R42,"OK")+COUNTIF(R46:R60,"?*")-COUNTIF(R46:R60,"OK")+COUNTIF(S18:S60,"rate?") | F102: must be 0 before the item counts as costed (see CHECK column)

Sheet PART LIST REFERENCE
A1: PART NUMBER | B1: NAME | C1: MATERIALS | F1: CODE | G1: MATERIAL | H1: THICKNESS mm | I1: VENEER | J1: DESCRIPTION
A2: 1 | B2: BOTTOM STRETCHER FRONT / BACK | C2: A | E2: A | F2: A | G2: Solid wood | J2: Solid wood
A3: 2 | B3: BOTTOM STRETCHER LEFT / RIGHT | C3: A | E3: A | F3: A1 | G3: Solid wood laminated | J3: Solid wood laminated
A4: 3 | B4: LEG (VERTICAL) | C4: A | E4: B | F4: B-3-0X | G4: Plywood | H4: 3 | I4: 0X | J4: Plywood 3 mm, no veneer
A5: 4 | B5: SHELFING | C5: - | E5: B | F5: B-3-1X | G5: Plywood | H5: 3 | I5: 1X | J5: Plywood 3 mm, veneer 1 face
A6: 5 | B6: DIVIDER | C6: B-9-0X | E6: B | F6: B-3-2X | G6: Plywood | H6: 3 | I6: 2X | J6: Plywood 3 mm, veneer 2 faces
A7: 6 | B7: FRONT DRAWER | C7: A | E7: B | F7: B-6-0X | G7: Plywood | H7: 6 | I7: 0X | J7: Plywood 6 mm, no veneer
A8: 7 | B8: INNER DRAWER | C8: B-6-1X | E8: B | F8: B-6-1X | G8: Plywood | H8: 6 | I8: 1X | J8: Plywood 6 mm, veneer 1 face
A9: 8 | B9: SIDE DRAWER | C9: B-12-0X | E9: B | F9: B-6-2X | G9: Plywood | H9: 6 | I9: 2X | J9: Plywood 6 mm, veneer 2 faces
A10: 9 | B10: BACK DRAWER | C10: B-12-0X | E10: B | F10: B-9-0X | G10: Plywood | H10: 9 | I10: 0X | J10: Plywood 9 mm, no veneer
A11: 10 | B11: BOTTOM DRAWER | C11: B-6-0X | E11: B | F11: B-9-1X | G11: Plywood | H11: 9 | I11: 1X | J11: Plywood 9 mm, veneer 1 face
A12: 11 | B12: DOOR PANEL | C12: - | E12: B | F12: B-9-2X | G12: Plywood | H12: 9 | I12: 2X | J12: Plywood 9 mm, veneer 2 faces
A13: 12 | B13: BACK PANEL | C13: B-9-0X | E13: B | F13: B-12-0X | G13: Plywood | H13: 12 | I13: 0X | J13: Plywood 12 mm, no veneer
A14: 13 | B14: SIDE PANEL | C14: B-12-1X | E14: B | F14: B-12-1X | G14: Plywood | H14: 12 | I14: 1X | J14: Plywood 12 mm, veneer 1 face
A15: 14 | B15: FRONT RAIL | C15: A | E15: B | F15: B-12-2X | G15: Plywood | H15: 12 | I15: 2X | J15: Plywood 12 mm, veneer 2 faces
... A21: 20 | B21: TOP PANEL | C21: B-18-1X | E21: B | F21: B-18-2X | G21: Plywood | H21: 18 | I21: 2X | J21: Plywood 18 mm, veneer 2 faces
E22: C | F22: C-3-0X | G22: MDF | H22: 3 | I22: 0X | J22: MDF 3 mm, no veneer
E23: C | F23: C-3-1X | G23: MDF | H23: 3 | I23: 1X | J23: MDF 3 mm, veneer 1 face
E24: C | F24: C-3-2X | G24: MDF | H24: 3 | I24: 2X | J24: MDF 3 mm, veneer 2 faces
E25: C | F25: C-6-0X | G25: MDF | H25: 6 | I25: 0X | J25: MDF 6 mm, no veneer
E26: C | F26: C-6-1X | G26: MDF | H26: 6 | I26: 1X | J26: MDF 6 mm, veneer 1 face
E27: C | F27: C-6-2X | G27: MDF | H27: 6 | I27: 2X | J27: MDF 6 mm, veneer 2 faces
E28: C | F28: C-9-0X | G28: MDF | H28: 9 | I28: 0X | J28: MDF 9 mm, no veneer
E29: C | F29: C-9-1X | G29: MDF | H29: 9 | I29: 1X | J29: MDF 9 mm, veneer 1 face
E30: C | F30: C-9-2X | G30: MDF | H30: 9 | I30: 2X | J30: MDF 9 mm, veneer 2 faces
E31: C | F31: C-12-0X | G31: MDF | H31: 12 | I31: 0X | J31: MDF 12 mm, no veneer
E32: C | F32: C-12-1X | G32: MDF | H32: 12 | I32: 1X | J32: MDF 12 mm, veneer 1 face
E33: C | F33: C-12-2X | G33: MDF | H33: 12 | I33: 2X | J33: MDF 12 mm, veneer 2 faces
... E39: C | F39: C-18-2X | G39: MDF | H39: 18 | I39: 2X | J39: MDF 18 mm, veneer 2 faces
E40: D | F40: D1 | G40: Hardware | J40: Soft close hinge DTC
E41: D | F41: D2 | G41: Hardware | J41: Drawer rail DTC (size follows drawer box side depth)
